{"filename":2014710626,"title":"Training for dancing, Japan","sort_date":1926,"thumb_url":"https://tile.loc.gov/storage-services/service/pnp/ggbain/30400/30469_150px.jpg#h=108&w=150","image_url":"https://tile.loc.gov/storage-services/service/pnp/ggbain/30400/30469v.jpg#h=739&w=1024","url":"https://www.loc.gov/item/2014710626/","height":739,"width":1024,"collection":"ggbain","face":[{"prob":0.9996,"x":905,"y":270,"height":14,"width":20},{"prob":0.9982,"x":304,"y":511,"height":28,"width":33},{"prob":0.9968,"x":681,"y":381,"height":20,"width":25},{"prob":0.9929,"x":172,"y":325,"height":17,"width":20},{"prob":0.9882,"x":467,"y":258,"height":13,"width":17},{"prob":0.9875,"x":52,"y":329,"height":19,"width":21},{"prob":0.9871,"x":600,"y":306,"height":17,"width":20},{"prob":0.9826,"x":730,"y":306,"height":17,"width":21},{"prob":0.9813,"x":785,"y":237,"height":12,"width":16},{"prob":0.9803,"x":379,"y":217,"height":11,"width":15},{"prob":0.9779,"x":51,"y":470,"height":24,"width":32},{"prob":0.9749,"x":831,"y":350,"height":16,"width":20},{"prob":0.9725,"x":253,"y":408,"height":21,"width":30},{"prob":0.9624,"x":980,"y":253,"height":13,"width":16},{"prob":0.8563,"x":912,"y":241,"height":12,"width":17}],"inst":[{"class":"person","prob":0.99,"x":370,"y":464,"height":255,"width":157},{"class":"person","prob":0.99,"x":476,"y":332,"height":200,"width":119},{"class":"person","prob":0.98,"x":592,"y":366,"height":172,"width":185},{"class":"person","prob":0.96,"x":588,"y":328,"height":164,"width":88},{"class":"person","prob":0.94,"x":948,"y":339,"height":237,"width":48},{"class":"person","prob":0.94,"x":282,"y":471,"height":246,"width":99},{"class":"person","prob":0.93,"x":122,"y":514,"height":205,"width":97},{"class":"person","prob":0.92,"x":754,"y":329,"height":190,"width":152},{"class":"person","prob":0.91,"x":124,"y":309,"height":185,"width":100},{"class":"person","prob":0.91,"x":274,"y":221,"height":148,"width":88},{"class":"person","prob":0.89,"x":165,"y":212,"height":114,"width":42},{"class":"person","prob":0.89,"x":708,"y":287,"height":180,"width":99},{"class":"person","prob":0.89,"x":46,"y":310,"height":179,"width":60},{"class":"person","prob":0.88,"x":114,"y":190,"height":116,"width":49},{"class":"person","prob":0.88,"x":213,"y":403,"height":293,"width":112},{"class":"person","prob":0.86,"x":40,"y":454,"height":262,"width":98},{"class":"person","prob":0.85,"x":81,"y":179,"height":127,"width":41},{"class":"person","prob":0.83,"x":80,"y":286,"height":163,"width":66},{"class":"person","prob":0.83,"x":376,"y":252,"height":163,"width":93},{"class":"person","prob":0.83,"x":575,"y":292,"height":141,"width":63},{"class":"tie","prob":0.82,"x":410,"y":532,"height":57,"width":15},{"class":"person","prob":0.82,"x":868,"y":260,"height":161,"width":103},{"class":"person","prob":0.81,"x":559,"y":184,"height":133,"width":75},{"class":"person","prob":0.8,"x":209,"y":184,"height":123,"width":65},{"class":"handbag","prob":0.78,"x":45,"y":547,"height":120,"width":75},{"class":"person","prob":0.77,"x":618,"y":184,"height":127,"width":68},{"class":"person","prob":0.75,"x":752,"y":224,"height":118,"width":67},{"class":"handbag","prob":0.74,"x":787,"y":405,"height":69,"width":74},{"class":"person","prob":0.73,"x":811,"y":219,"height":124,"width":49},{"class":"tie","prob":0.7,"x":414,"y":291,"height":33,"width":11},{"class":"person","prob":0.61,"x":494,"y":216,"height":82,"width":63},{"class":"person","prob":0.61,"x":646,"y":204,"height":123,"width":70},{"class":"person","prob":0.61,"x":446,"y":252,"height":149,"width":63},{"class":"person","prob":0.6,"x":492,"y":152,"height":85,"width":44},{"class":"person","prob":0.6,"x":351,"y":207,"height":123,"width":66},{"class":"person","prob":0.59,"x":210,"y":386,"height":102,"width":130},{"class":"tie","prob":0.58,"x":275,"y":484,"height":37,"width":16}],"kcnt":[{"index":0,"x0":704,"y0":393,"score0":0.63,"x1":692,"y1":391,"score1":0.76},{"index":0,"x0":729,"y0":438,"score0":0.24,"x1":754,"y1":453,"score1":0.22},{"index":0,"x0":692,"y0":391,"score0":0.76,"x1":687,"y1":395,"score1":0.83},{"index":0,"x0":690,"y0":482,"score0":0.1,"x1":669,"y1":472,"score1":0.12},{"index":0,"x0":690,"y0":482,"score0":0.1,"x1":682,"y1":529,"score1":0.09},{"index":0,"x0":682,"y0":529,"score0":0.09,"x1":651,"y1":515,"score1":0.04},{"index":0,"x0":710,"y0":419,"score0":0.17,"x1":677,"y1":405,"score1":0.14},{"index":0,"x0":710,"y0":419,"score0":0.17,"x1":729,"y1":438,"score1":0.24},{"index":0,"x0":687,"y0":395,"score0":0.83,"x1":684,"y1":389,"score1":1.16},{"index":0,"x0":679,"y0":390,"score0":0.38,"x1":684,"y1":389,"score1":1.16},{"index":0,"x0":672,"y0":435,"score0":0.04,"x1":664,"y1":467,"score1":0.02},{"index":0,"x0":669,"y0":472,"score0":0.12,"x1":630,"y1":475,"score1":0.15},{"index":0,"x0":630,"y0":475,"score0":0.15,"x1":651,"y1":514,"score1":0.07},{"index":0,"x0":677,"y0":405,"score0":0.14,"x1":672,"y1":435,"score1":0.04},{"index":1,"x0":556,"y0":360,"score0":0.41,"x1":548,"y1":360,"score1":0.55},{"index":1,"x0":573,"y0":409,"score0":0.15,"x1":585,"y1":423,"score1":0.22},{"index":1,"x0":548,"y0":360,"score0":0.55,"x1":543,"y1":362,"score1":0.46},{"index":1,"x0":535,"y0":434,"score0":0.14,"x1":519,"y1":430,"score1":0.11},{"index":1,"x0":535,"y0":434,"score0":0.14,"x1":496,"y1":458,"score1":0.14},{"index":1,"x0":496,"y0":458,"score0":0.14,"x1":535,"y1":515,"score1":0.2},{"index":1,"x0":555,"y0":381,"score0":0.21,"x1":523,"y1":353,"score1":0.19},{"index":1,"x0":555,"y0":381,"score0":0.21,"x1":573,"y1":409,"score1":0.15},{"index":1,"x0":543,"y0":362,"score0":0.46,"x1":540,"y1":357,"score1":0.49},{"index":1,"x0":535,"y0":349,"score0":0.52,"x1":540,"y1":357,"score1":0.49},{"index":1,"x0":498,"y0":328,"score0":0.11,"x1":497,"y1":328,"score1":0.05},{"index":1,"x0":519,"y0":430,"score0":0.11,"x1":526,"y1":472,"score1":0.06},{"index":1,"x0":526,"y0":472,"score0":0.06,"x1":490,"y1":496,"score1":0.13},{"index":1,"x0":523,"y0":353,"score0":0.19,"x1":498,"y1":328,"score1":0.11},{"index":2,"x0":663,"y0":351,"score0":0.29,"x1":655,"y1":351,"score1":0.27},{"index":2,"x0":673,"y0":420,"score0":0.04,"x1":671,"y1":444,"score1":0.01},{"index":2,"x0":655,"y0":351,"score0":0.27,"x1":651,"y1":355,"score1":0.31},{"index":2,"x0":649,"y0":432,"score0":0.03,"x1":626,"y1":429,"score1":0.05},{"index":2,"x0":649,"y0":432,"score0":0.03,"x1":610,"y1":447,"score1":0.05},{"index":2,"x0":610,"y0":447,"score0":0.05,"x1":612,"y1":483,"score1":0.02},{"index":2,"x0":666,"y0":384,"score0":0.08,"x1":636,"y1":359,"score1":0.13},{"index":2,"x0":666,"y0":384,"score0":0.08,"x1":673,"y1":420,"score1":0.04},{"index":2,"x0":651,"y0":355,"score0":0.31,"x1":645,"y1":351,"score1":0.24},{"index":2,"x0":638,"y0":350,"score0":0.35,"x1":645,"y1":351,"score1":0.24},{"index":2,"x0":619,"y0":347,"score0":0.11,"x1":603,"y1":332,"score1":0.06},{"index":2,"x0":626,"y0":429,"score0":0.05,"x1":606,"y1":448,"score1":0.03},{"index":2,"x0":606,"y0":448,"score0":0.03,"x1":610,"y1":483,"score1":0.02},{"index":2,"x0":636,"y0":359,"score0":0.13,"x1":619,"y1":347,"score1":0.11},{"index":3,"x0":431,"y0":504,"score0":0.41,"x1":411,"y1":505,"score1":0.43},{"index":3,"x0":483,"y0":537,"score0":0.07,"x1":410,"y1":612,"score1":0.01},{"index":3,"x0":411,"y0":505,"score0":0.43,"x1":408,"y1":511,"score1":0.5},{"index":3,"x0":443,"y0":635,"score0":0.04,"x1":417,"y1":631,"score1":0.05},{"index":3,"x0":443,"y0":635,"score0":0.04,"x1":447,"y1":709,"score1":0.02},{"index":3,"x0":447,"y0":709,"score0":0.02,"x1":449,"y1":722,"score1":0.03},{"index":3,"x0":441,"y0":534,"score0":0.04,"x1":423,"y1":526,"score1":0.04},{"index":3,"x0":441,"y0":534,"score0":0.04,"x1":483,"y1":537,"score1":0.07},{"index":3,"x0":408,"y0":511,"score0":0.5,"x1":408,"y1":504,"score1":0.39},{"index":3,"x0":431,"y0":503,"score0":0.16,"x1":408,"y1":504,"score1":0.39},{"index":3,"x0":391,"y0":504,"score0":0.04,"x1":378,"y1":518,"score1":0.03},{"index":3,"x0":417,"y0":631,"score0":0.05,"x1":401,"y1":711,"score1":0.02},{"index":3,"x0":401,"y0":711,"score0":0.02,"x1":389,"y1":722,"score1":0.02},{"index":3,"x0":423,"y0":526,"score0":0.04,"x1":391,"y1":504,"score1":0.04},{"index":4,"x0":75,"y0":336,"score0":0.18,"x1":63,"y1":337,"score1":0.37},{"index":4,"x0":84,"y0":394,"score0":0.07,"x1":82,"y1":382,"score1":0.02},{"index":4,"x0":63,"y0":337,"score0":0.37,"x1":59,"y1":342,"score1":0.24},{"index":4,"x0":82,"y0":416,"score0":0.02,"x1":63,"y1":414,"score1":0.05},{"index":4,"x0":82,"y0":416,"score0":0.02,"x1":88,"y1":461,"score1":0.02},{"index":4,"x0":88,"y0":461,"score0":0.02,"x1":103,"y1":469,"score1":0.03},{"index":4,"x0":84,"y0":355,"score0":0.09,"x1":56,"y1":358,"score1":0.05},{"index":4,"x0":84,"y0":355,"score0":0.09,"x1":84,"y1":394,"score1":0.07},{"index":4,"x0":59,"y0":342,"score0":0.24,"x1":55,"y1":338,"score1":0.37},{"index":4,"x0":52,"y0":338,"score0":0.18,"x1":55,"y1":338,"score1":0.37},{"index":4,"x0":47,"y0":403,"score0":0.07,"x1":50,"y1":360,"score1":0.07},{"index":4,"x0":63,"y0":414,"score0":0.05,"x1":51,"y1":455,"score1":0.02},{"index":4,"x0":51,"y0":455,"score0":0.02,"x1":73,"y1":469,"score1":0.02},{"index":4,"x0":56,"y0":358,"score0":0.05,"x1":47,"y1":403,"score1":0.07},{"index":5,"x0":983,"y0":359,"score0":0.13,"x1":974,"y1":355,"score1":0.09},{"index":5,"x0":987,"y0":428,"score0":0.15,"x1":971,"y1":455,"score1":0.12},{"index":5,"x0":974,"y0":355,"score0":0.09,"x1":971,"y1":359,"score1":0.1},{"index":5,"x0":973,"y0":446,"score0":0.02,"x1":961,"y1":439,"score1":0.03},{"index":5,"x0":973,"y0":446,"score0":0.02,"x1":973,"y1":502,"score1":0.04},{"index":5,"x0":973,"y0":502,"score0":0.04,"x1":974,"y1":552,"score1":0.09},{"index":5,"x0":989,"y0":390,"score0":0.08,"x1":976,"y1":376,"score1":0.05},{"index":5,"x0":989,"y0":390,"score0":0.08,"x1":987,"y1":428,"score1":0.15},{"index":5,"x0":971,"y0":359,"score0":0.1,"x1":973,"y1":355,"score1":0.09},{"index":5,"x0":981,"y0":357,"score0":0.02,"x1":973,"y1":355,"score1":0.09},{"index":5,"x0":965,"y0":401,"score0":0.03,"x1":956,"y1":413,"score1":0.03},{"index":5,"x0":961,"y0":439,"score0":0.03,"x1":961,"y1":492,"score1":0.03},{"index":5,"x0":961,"y0":492,"score0":0.03,"x1":965,"y1":537,"score1":0.02},{"index":5,"x0":976,"y0":376,"score0":0.05,"x1":965,"y1":401,"score1":0.03},{"index":6,"x0":334,"y0":521,"score0":0.24,"x1":317,"y1":524,"score1":0.55},{"index":6,"x0":360,"y0":585,"score0":0.09,"x1":373,"y1":614,"score1":0.06},{"index":6,"x0":317,"y0":524,"score0":0.55,"x1":310,"y1":530,"score1":0.88},{"index":6,"x0":345,"y0":639,"score0":0.03,"x1":314,"y1":637,"score1":0.03},{"index":6,"x0":345,"y0":639,"score0":0.03,"x1":360,"y1":693,"score1":0.03},{"index":6,"x0":360,"y0":693,"score0":0.03,"x1":296,"y1":708,"score1":0.03},{"index":6,"x0":347,"y0":556,"score0":0.09,"x1":316,"y1":545,"score1":0.05},{"index":6,"x0":347,"y0":556,"score0":0.09,"x1":360,"y1":585,"score1":0.09},{"index":6,"x0":310,"y0":530,"score0":0.88,"x1":306,"y1":522,"score1":0.73},{"index":6,"x0":304,"y0":519,"score0":0.07,"x1":306,"y1":522,"score1":0.73},{"index":6,"x0":295,"y0":583,"score0":0.02,"x1":295,"y1":590,"score1":0.07},{"index":6,"x0":314,"y0":637,"score0":0.03,"x1":326,"y1":702,"score1":0.01},{"index":6,"x0":326,"y0":702,"score0":0.01,"x1":295,"y1":709,"score1":0.02},{"index":6,"x0":316,"y0":545,"score0":0.05,"x1":295,"y1":583,"score1":0.02},{"index":7,"x0":849,"y0":362,"score0":0.56,"x1":841,"y1":361,"score1":0.74},{"index":7,"x0":875,"y0":392,"score0":0.16,"x1":898,"y1":416,"score1":0.1},{"index":7,"x0":841,"y0":361,"score0":0.74,"x1":836,"y1":362,"score1":0.69},{"index":7,"x0":838,"y0":426,"score0":0.07,"x1":817,"y1":420,"score1":0.12},{"index":7,"x0":838,"y0":426,"score0":0.07,"x1":792,"y1":454,"score1":0.14},{"index":7,"x0":792,"y0":454,"score0":0.14,"x1":762,"y1":481,"score1":0.14},{"index":7,"x0":853,"y0":381,"score0":0.21,"x1":824,"y1":361,"score1":0.11},{"index":7,"x0":853,"y0":381,"score0":0.21,"x1":875,"y1":392,"score1":0.16},{"index":7,"x0":836,"y0":362,"score0":0.69,"x1":835,"y1":357,"score1":0.9},{"index":7,"x0":832,"y0":353,"score0":0.3,"x1":835,"y1":357,"score1":0.9},{"index":7,"x0":791,"y0":343,"score0":0.05,"x1":795,"y1":347,"score1":0.07},{"index":7,"x0":817,"y0":420,"score0":0.12,"x1":814,"y1":457,"score1":0.05},{"index":7,"x0":814,"y0":457,"score0":0.05,"x1":826,"y1":506,"score1":0.13},{"index":7,"x0":824,"y0":361,"score0":0.11,"x1":791,"y1":343,"score1":0.05},{"index":8,"x0":157,"y0":554,"score0":0.18,"x1":140,"y1":553,"score1":0.42},{"index":8,"x0":194,"y0":644,"score0":0.08,"x1":166,"y1":680,"score1":0.03},{"index":8,"x0":140,"y0":553,"score0":0.42,"x1":137,"y1":561,"score1":0.5},{"index":8,"x0":179,"y0":701,"score0":0.03,"x1":161,"y1":701,"score1":0.01},{"index":8,"x0":179,"y0":701,"score0":0.03,"x1":194,"y1":711,"score1":0.01},{"index":8,"x0":194,"y0":711,"score0":0.01,"x1":221,"y1":722,"score1":0.05},{"index":8,"x0":182,"y0":589,"score0":0.09,"x1":148,"y1":579,"score1":0.04},{"index":8,"x0":182,"y0":589,"score0":0.09,"x1":194,"y1":644,"score1":0.08},{"index":8,"x0":137,"y0":561,"score0":0.5,"x1":138,"y1":553,"score1":0.38},{"index":8,"x0":157,"y0":553,"score0":0.06,"x1":138,"y1":553,"score1":0.38},{"index":8,"x0":139,"y0":622,"score0":0.03,"x1":221,"y1":722,"score1":0.02},{"index":8,"x0":161,"y0":701,"score0":0.01,"x1":160,"y1":722,"score1":0.02},{"index":8,"x0":160,"y0":722,"score0":0.02,"x1":157,"y1":722,"score1":0.02},{"index":8,"x0":148,"y0":579,"score0":0.04,"x1":139,"y1":622,"score1":0.03},{"index":9,"x0":332,"y0":243,"score0":0.25,"x1":321,"y1":243,"score1":0.36},{"index":9,"x0":349,"y0":266,"score0":0.07,"x1":363,"y1":271,"score1":0.1},{"index":9,"x0":321,"y0":243,"score0":0.36,"x1":317,"y1":245,"score1":0.45},{"index":9,"x0":324,"y0":299,"score0":0.08,"x1":312,"y1":295,"score1":0.12},{"index":9,"x0":324,"y0":299,"score0":0.08,"x1":316,"y1":330,"score1":0.07},{"index":9,"x0":316,"y0":330,"score0":0.07,"x1":327,"y1":362,"score1":0.12},{"index":9,"x0":335,"y0":258,"score0":0.19,"x1":316,"y1":253,"score1":0.15},{"index":9,"x0":335,"y0":258,"score0":0.19,"x1":349,"y1":266,"score1":0.07},{"index":9,"x0":317,"y0":245,"score0":0.45,"x1":316,"y1":241,"score1":0.4},{"index":9,"x0":317,"y0":238,"score0":0.06,"x1":316,"y1":241,"score1":0.4},{"index":9,"x0":308,"y0":236,"score0":0.05,"x1":363,"y1":271,"score1":0.04},{"index":9,"x0":312,"y0":295,"score0":0.12,"x1":291,"y1":308,"score1":0.07},{"index":9,"x0":291,"y0":308,"score0":0.07,"x1":287,"y1":340,"score1":0.21},{"index":9,"x0":316,"y0":253,"score0":0.15,"x1":308,"y1":236,"score1":0.05},{"index":10,"x0":194,"y0":329,"score0":0.37,"x1":182,"y1":331,"score1":0.58},{"index":10,"x0":200,"y0":365,"score0":0.03,"x1":195,"y1":396,"score1":0.03},{"index":10,"x0":182,"y0":331,"score0":0.58,"x1":178,"y1":337,"score1":0.66},{"index":10,"x0":185,"y0":401,"score0":0.05,"x1":175,"y1":401,"score1":0.04},{"index":10,"x0":185,"y0":401,"score0":0.05,"x1":146,"y1":428,"score1":0.07},{"index":10,"x0":146,"y0":428,"score0":0.07,"x1":192,"y1":477,"score1":0.07},{"index":10,"x0":197,"y0":350,"score0":0.13,"x1":183,"y1":348,"score1":0.05},{"index":10,"x0":197,"y0":350,"score0":0.13,"x1":200,"y1":365,"score1":0.03},{"index":10,"x0":178,"y0":337,"score0":0.66,"x1":175,"y1":333,"score1":0.58},{"index":10,"x0":172,"y0":334,"score0":0.25,"x1":175,"y1":333,"score1":0.58},{"index":10,"x0":174,"y0":326,"score0":0.03,"x1":194,"y1":324,"score1":0.02},{"index":10,"x0":175,"y0":401,"score0":0.04,"x1":144,"y1":430,"score1":0.03},{"index":10,"x0":144,"y0":430,"score0":0.03,"x1":137,"y1":473,"score1":0.07},{"index":10,"x0":183,"y0":348,"score0":0.05,"x1":174,"y1":326,"score1":0.03},{"index":11,"x0":750,"y0":314,"score0":0.4,"x1":741,"y1":313,"score1":0.57},{"index":11,"x0":784,"y0":341,"score0":0.12,"x1":798,"y1":346,"score1":0.08},{"index":11,"x0":741,"y0":313,"score0":0.57,"x1":736,"y1":318,"score1":0.68},{"index":11,"x0":748,"y0":395,"score0":0.05,"x1":725,"y1":390,"score1":0.06},{"index":11,"x0":748,"y0":395,"score0":0.05,"x1":742,"y1":445,"score1":0.05},{"index":11,"x0":742,"y0":445,"score0":0.05,"x1":745,"y1":452,"score1":0.03},{"index":11,"x0":759,"y0":335,"score0":0.13,"x1":728,"y1":330,"score1":0.13},{"index":11,"x0":759,"y0":335,"score0":0.13,"x1":784,"y1":341,"score1":0.12},{"index":11,"x0":736,"y0":318,"score0":0.68,"x1":733,"y1":313,"score1":0.64},{"index":11,"x0":729,"y0":315,"score0":0.38,"x1":733,"y1":313,"score1":0.64},{"index":11,"x0":722,"y0":364,"score0":0.03,"x1":720,"y1":385,"score1":0.04},{"index":11,"x0":725,"y0":390,"score0":0.06,"x1":724,"y1":442,"score1":0.02},{"index":11,"x0":724,"y0":442,"score0":0.02,"x1":752,"y1":452,"score1":0.03},{"index":11,"x0":728,"y0":330,"score0":0.13,"x1":722,"y1":364,"score1":0.03},{"index":12,"x0":81,"y0":483,"score0":0.5,"x1":63,"y1":482,"score1":0.64},{"index":12,"x0":113,"y0":529,"score0":0.04,"x1":126,"y1":506,"score1":0.06},{"index":12,"x0":63,"y0":482,"score0":0.64,"x1":57,"y1":487,"score1":0.63},{"index":12,"x0":94,"y0":590,"score0":0.06,"x1":72,"y1":579,"score1":0.04},{"index":12,"x0":94,"y0":590,"score0":0.06,"x1":92,"y1":652,"score1":0.05},{"index":12,"x0":92,"y0":652,"score0":0.05,"x1":103,"y1":716,"score1":0.09},{"index":12,"x0":96,"y0":514,"score0":0.12,"x1":73,"y1":507,"score1":0.07},{"index":12,"x0":96,"y0":514,"score0":0.12,"x1":113,"y1":529,"score1":0.04},{"index":12,"x0":57,"y0":487,"score0":0.63,"x1":53,"y1":482,"score1":0.59},{"index":12,"x0":82,"y0":482,"score0":0.22,"x1":53,"y1":482,"score1":0.59},{"index":12,"x0":59,"y0":545,"score0":0.05,"x1":52,"y1":526,"score1":0.02},{"index":12,"x0":72,"y0":579,"score0":0.04,"x1":87,"y1":650,"score1":0.08},{"index":12,"x0":87,"y0":650,"score0":0.08,"x1":100,"y1":705,"score1":0.07},{"index":12,"x0":73,"y0":507,"score0":0.07,"x1":59,"y1":545,"score1":0.05},{"index":13,"x0":921,"y0":278,"score0":0.44,"x1":918,"y1":277,"score1":0.69},{"index":13,"x0":946,"y0":297,"score0":0.17,"x1":959,"y1":304,"score1":0.07},{"index":13,"x0":918,"y0":277,"score0":0.69,"x1":915,"y1":281,"score1":1.09},{"index":13,"x0":915,"y0":345,"score0":0.08,"x1":895,"y1":343,"score1":0.08},{"index":13,"x0":915,"y0":345,"score0":0.08,"x1":916,"y1":380,"score1":0.09},{"index":13,"x0":916,"y0":380,"score0":0.09,"x1":899,"y1":411,"score1":0.03},{"index":13,"x0":925,"y0":297,"score0":0.18,"x1":896,"y1":296,"score1":0.17},{"index":13,"x0":925,"y0":297,"score0":0.18,"x1":946,"y1":297,"score1":0.17},{"index":13,"x0":915,"y0":281,"score0":1.09,"x1":911,"y1":277,"score1":0.74},{"index":13,"x0":903,"y0":278,"score0":0.7,"x1":911,"y1":277,"score1":0.74},{"index":13,"x0":882,"y0":273,"score0":0.14,"x1":889,"y1":257,"score1":0.23},{"index":13,"x0":895,"y0":343,"score0":0.08,"x1":895,"y1":380,"score1":0.11},{"index":13,"x0":895,"y0":380,"score0":0.11,"x1":898,"y1":411,"score1":0.16},{"index":13,"x0":896,"y0":296,"score0":0.17,"x1":882,"y1":273,"score1":0.14},{"index":14,"x0":392,"y0":223,"score0":0.38,"x1":386,"y1":223,"score1":0.4},{"index":14,"x0":413,"y0":251,"score0":0.09,"x1":402,"y1":271,"score1":0.05},{"index":14,"x0":386,"y0":223,"score0":0.4,"x1":383,"y1":225,"score1":0.42},{"index":14,"x0":391,"y0":282,"score0":0.07,"x1":375,"y1":279,"score1":0.1},{"index":14,"x0":391,"y0":282,"score0":0.07,"x1":398,"y1":319,"score1":0.03},{"index":14,"x0":398,"y0":319,"score0":0.03,"x1":356,"y1":323,"score1":0.02},{"index":14,"x0":397,"y0":237,"score0":0.12,"x1":378,"y1":235,"score1":0.15},{"index":14,"x0":397,"y0":237,"score0":0.12,"x1":413,"y1":251,"score1":0.09},{"index":14,"x0":383,"y0":225,"score0":0.42,"x1":381,"y1":222,"score1":0.49},{"index":14,"x0":378,"y0":223,"score0":0.31,"x1":381,"y1":222,"score1":0.49},{"index":14,"x0":366,"y0":248,"score0":0.06,"x1":349,"y1":261,"score1":0.01},{"index":14,"x0":375,"y0":279,"score0":0.1,"x1":354,"y1":292,"score1":0.15},{"index":14,"x0":354,"y0":292,"score0":0.15,"x1":356,"y1":321,"score1":0.07},{"index":14,"x0":378,"y0":235,"score0":0.15,"x1":366,"y1":248,"score1":0.06},{"index":15,"x0":105,"y0":309,"score0":0.15,"x1":96,"y1":312,"score1":0.14},{"index":15,"x0":130,"y0":330,"score0":0.07,"x1":139,"y1":333,"score1":0.08},{"index":15,"x0":96,"y0":312,"score0":0.14,"x1":94,"y1":317,"score1":0.12},{"index":15,"x0":115,"y0":369,"score0":0.07,"x1":97,"y1":369,"score1":0.04},{"index":15,"x0":115,"y0":369,"score0":0.07,"x1":118,"y1":408,"score1":0.07},{"index":15,"x0":118,"y0":408,"score0":0.07,"x1":120,"y1":444,"score1":0.14},{"index":15,"x0":117,"y0":325,"score0":0.12,"x1":92,"y1":331,"score1":0.07},{"index":15,"x0":117,"y0":325,"score0":0.12,"x1":130,"y1":330,"score1":0.07},{"index":15,"x0":94,"y0":317,"score0":0.12,"x1":89,"y1":316,"score1":0.13},{"index":15,"x0":87,"y0":316,"score0":0.07,"x1":89,"y1":316,"score1":0.13},{"index":15,"x0":87,"y0":350,"score0":0.03,"x1":87,"y1":346,"score1":0.01},{"index":15,"x0":97,"y0":369,"score0":0.04,"x1":96,"y1":411,"score1":0.03},{"index":15,"x0":96,"y0":411,"score0":0.03,"x1":94,"y1":444,"score1":0.02},{"index":15,"x0":92,"y0":331,"score0":0.07,"x1":87,"y1":350,"score1":0.03},{"index":16,"x0":300,"y0":456,"score0":0.4,"x1":291,"y1":461,"score1":0.89},{"index":16,"x0":294,"y0":534,"score0":0.02,"x1":288,"y1":500,"score1":0.02},{"index":16,"x0":291,"y0":461,"score0":0.89,"x1":286,"y1":468,"score1":1.18},{"index":16,"x0":301,"y0":541,"score0":0.01,"x1":282,"y1":539,"score1":0.02},{"index":16,"x0":301,"y0":541,"score0":0.01,"x1":289,"y1":573,"score1":0.01},{"index":16,"x0":289,"y0":573,"score0":0.01,"x1":239,"y1":629,"score1":0.01},{"index":16,"x0":317,"y0":478,"score0":0.04,"x1":274,"y1":478,"score1":0.09},{"index":16,"x0":317,"y0":478,"score0":0.04,"x1":294,"y1":534,"score1":0.02},{"index":16,"x0":286,"y0":468,"score0":1.18,"x1":279,"y1":463,"score1":0.77},{"index":16,"x0":270,"y0":460,"score0":0.3,"x1":279,"y1":463,"score1":0.77},{"index":16,"x0":237,"y0":456,"score0":0.05,"x1":235,"y1":444,"score1":0.09},{"index":16,"x0":282,"y0":539,"score0":0.02,"x1":239,"y1":556,"score1":0.07},{"index":16,"x0":239,"y0":556,"score0":0.07,"x1":224,"y1":617,"score1":0.05},{"index":16,"x0":274,"y0":478,"score0":0.09,"x1":237,"y1":456,"score1":0.05},{"index":17,"x0":152,"y0":208,"score0":0.18,"x1":145,"y1":208,"score1":0.12},{"index":17,"x0":156,"y0":245,"score0":0.02,"x1":156,"y1":220,"score1":0.01},{"index":17,"x0":145,"y0":208,"score0":0.12,"x1":143,"y1":210,"score1":0.14},{"index":17,"x0":152,"y0":254,"score0":0.03,"x1":141,"y1":253,"score1":0.04},{"index":17,"x0":152,"y0":254,"score0":0.03,"x1":124,"y1":267,"score1":0.1},{"index":17,"x0":124,"y0":267,"score0":0.1,"x1":122,"y1":292,"score1":0.07},{"index":17,"x0":155,"y0":221,"score0":0.05,"x1":140,"y1":221,"score1":0.07},{"index":17,"x0":155,"y0":221,"score0":0.05,"x1":156,"y1":245,"score1":0.02},{"index":17,"x0":143,"y0":210,"score0":0.14,"x1":141,"y1":208,"score1":0.16},{"index":17,"x0":138,"y0":206,"score0":0.13,"x1":141,"y1":208,"score1":0.16},{"index":17,"x0":133,"y0":241,"score0":0.03,"x1":129,"y1":251,"score1":0.05},{"index":17,"x0":141,"y0":253,"score0":0.04,"x1":124,"y1":265,"score1":0.05},{"index":17,"x0":124,"y0":265,"score0":0.05,"x1":123,"y1":290,"score1":0.04},{"index":17,"x0":140,"y0":221,"score0":0.07,"x1":133,"y1":241,"score1":0.03},{"index":18,"x0":95,"y0":195,"score0":0.1,"x1":89,"y1":197,"score1":0.15},{"index":18,"x0":114,"y0":220,"score0":0.02,"x1":112,"y1":225,"score1":0.01},{"index":18,"x0":89,"y0":197,"score0":0.15,"x1":87,"y1":199,"score1":0.12},{"index":18,"x0":107,"y0":241,"score0":0.03,"x1":94,"y1":241,"score1":0.05},{"index":18,"x0":107,"y0":241,"score0":0.03,"x1":107,"y1":268,"score1":0.03},{"index":18,"x0":107,"y0":268,"score0":0.03,"x1":109,"y1":289,"score1":0.04},{"index":18,"x0":106,"y0":206,"score0":0.04,"x1":90,"y1":207,"score1":0.03},{"index":18,"x0":106,"y0":206,"score0":0.04,"x1":114,"y1":220,"score1":0.02},{"index":18,"x0":87,"y0":199,"score0":0.12,"x1":87,"y1":197,"score1":0.05},{"index":18,"x0":107,"y0":188,"score0":0.06,"x1":87,"y1":197,"score1":0.05},{"index":18,"x0":113,"y0":219,"score0":0.02,"x1":117,"y1":230,"score1":0.01},{"index":18,"x0":94,"y0":241,"score0":0.05,"x1":92,"y1":273,"score1":0.03},{"index":18,"x0":92,"y0":273,"score0":0.03,"x1":92,"y1":294,"score1":0.02},{"index":18,"x0":90,"y0":207,"score0":0.03,"x1":113,"y1":219,"score1":0.02},{"index":19,"x0":618,"y0":315,"score0":0.27,"x1":611,"y1":313,"score1":0.33},{"index":19,"x0":635,"y0":359,"score0":0.05,"x1":596,"y1":315,"score1":0.11},{"index":19,"x0":611,"y0":313,"score0":0.33,"x1":607,"y1":318,"score1":0.34},{"index":19,"x0":614,"y0":387,"score0":0.01,"x1":594,"y1":392,"score1":0.01},{"index":19,"x0":614,"y0":387,"score0":0.01,"x1":609,"y1":427,"score1":0.01},{"index":19,"x0":609,"y0":427,"score0":0.01,"x1":608,"y1":423,"score1":0.01},{"index":19,"x0":628,"y0":334,"score0":0.06,"x1":600,"y1":335,"score1":0.06},{"index":19,"x0":628,"y0":334,"score0":0.06,"x1":635,"y1":359,"score1":0.05},{"index":19,"x0":607,"y0":318,"score0":0.34,"x1":603,"y1":314,"score1":0.32},{"index":19,"x0":599,"y0":315,"score0":0.12,"x1":603,"y1":314,"score1":0.32},{"index":19,"x0":583,"y0":315,"score0":0.01,"x1":594,"y1":313,"score1":0.01},{"index":19,"x0":594,"y0":392,"score0":0.01,"x1":574,"y1":433,"score1":0.02},{"index":19,"x0":574,"y0":433,"score0":0.02,"x1":574,"y1":433,"score1":0.02},{"index":19,"x0":600,"y0":335,"score0":0.06,"x1":583,"y1":315,"score1":0.01},{"index":20,"x0":190,"y0":227,"score0":0.16,"x1":182,"y1":225,"score1":0.16},{"index":20,"x0":196,"y0":262,"score0":0.08,"x1":194,"y1":280,"score1":0.12},{"index":20,"x0":182,"y0":225,"score0":0.16,"x1":179,"y1":229,"score1":0.15},{"index":20,"x0":188,"y0":275,"score0":0.02,"x1":180,"y1":272,"score1":0.02},{"index":20,"x0":188,"y0":275,"score0":0.02,"x1":181,"y1":305,"score1":0.01},{"index":20,"x0":181,"y0":305,"score0":0.01,"x1":196,"y1":322,"score1":0.02},{"index":20,"x0":197,"y0":243,"score0":0.07,"x1":183,"y1":241,"score1":0.04},{"index":20,"x0":197,"y0":243,"score0":0.07,"x1":196,"y1":262,"score1":0.08},{"index":20,"x0":179,"y0":229,"score0":0.15,"x1":177,"y1":226,"score1":0.19},{"index":20,"x0":174,"y0":228,"score0":0.13,"x1":177,"y1":226,"score1":0.19},{"index":20,"x0":170,"y0":250,"score0":0.02,"x1":166,"y1":247,"score1":0.02},{"index":20,"x0":180,"y0":272,"score0":0.02,"x1":171,"y1":303,"score1":0.01},{"index":20,"x0":171,"y0":303,"score0":0.01,"x1":170,"y1":305,"score1":0.01},{"index":20,"x0":183,"y0":241,"score0":0.04,"x1":170,"y1":250,"score1":0.02},{"index":21,"x0":483,"y0":267,"score0":0.36,"x1":477,"y1":264,"score1":0.37},{"index":21,"x0":498,"y0":289,"score0":0.04,"x1":513,"y1":297,"score1":0.05},{"index":21,"x0":477,"y0":264,"score0":0.37,"x1":472,"y1":268,"score1":0.31},{"index":21,"x0":484,"y0":322,"score0":0.03,"x1":464,"y1":319,"score1":0.02},{"index":21,"x0":484,"y0":322,"score0":0.03,"x1":475,"y1":353,"score1":0.02},{"index":21,"x0":475,"y0":353,"score0":0.02,"x1":476,"y1":384,"score1":0.07},{"index":21,"x0":489,"y0":281,"score0":0.08,"x1":462,"y1":282,"score1":0.08},{"index":21,"x0":489,"y0":281,"score0":0.08,"x1":498,"y1":289,"score1":0.04},{"index":21,"x0":472,"y0":268,"score0":0.31,"x1":470,"y1":265,"score1":0.37},{"index":21,"x0":466,"y0":267,"score0":0.3,"x1":470,"y1":265,"score1":0.37},{"index":21,"x0":454,"y0":304,"score0":0.02,"x1":458,"y1":301,"score1":0.01},{"index":21,"x0":464,"y0":319,"score0":0.02,"x1":467,"y1":352,"score1":0.06},{"index":21,"x0":467,"y0":352,"score0":0.06,"x1":475,"y1":383,"score1":0.13},{"index":21,"x0":462,"y0":282,"score0":0.08,"x1":454,"y1":304,"score1":0.02},{"index":22,"x0":515,"y0":165,"score0":0.14,"x1":512,"y1":161,"score1":0.11},{"index":22,"x0":529,"y0":178,"score0":0.11,"x1":529,"y1":178,"score1":0.12},{"index":22,"x0":512,"y0":161,"score0":0.11,"x1":510,"y1":164,"score1":0.12},{"index":22,"x0":512,"y0":201,"score0":0.05,"x1":501,"y1":200,"score1":0.05},{"index":22,"x0":512,"y0":201,"score0":0.05,"x1":514,"y1":220,"score1":0.03},{"index":22,"x0":514,"y0":220,"score0":0.03,"x1":515,"y1":230,"score1":0.03},{"index":22,"x0":516,"y0":176,"score0":0.08,"x1":502,"y1":174,"score1":0.08},{"index":22,"x0":516,"y0":176,"score0":0.08,"x1":529,"y1":178,"score1":0.11},{"index":22,"x0":510,"y0":164,"score0":0.12,"x1":508,"y1":161,"score1":0.14},{"index":22,"x0":504,"y0":163,"score0":0.15,"x1":508,"y1":161,"score1":0.14},{"index":22,"x0":498,"y0":188,"score0":0.06,"x1":496,"y1":196,"score1":0.04},{"index":22,"x0":501,"y0":200,"score0":0.05,"x1":501,"y1":217,"score1":0.02},{"index":22,"x0":501,"y0":217,"score0":0.02,"x1":509,"y1":226,"score1":0.01},{"index":22,"x0":502,"y0":174,"score0":0.08,"x1":498,"y1":188,"score1":0.06},{"index":23,"x0":442,"y0":274,"score0":0.33,"x1":433,"y1":276,"score1":0.34},{"index":23,"x0":448,"y0":323,"score0":0.02,"x1":450,"y1":323,"score1":0.03},{"index":23,"x0":433,"y0":276,"score0":0.34,"x1":429,"y1":279,"score1":0.38},{"index":23,"x0":440,"y0":337,"score0":0.03,"x1":424,"y1":336,"score1":0.04},{"index":23,"x0":440,"y0":337,"score0":0.03,"x1":426,"y1":367,"score1":0.02},{"index":23,"x0":426,"y0":367,"score0":0.02,"x1":433,"y1":401,"score1":0.05},{"index":23,"x0":450,"y0":289,"score0":0.08,"x1":424,"y1":293,"score1":0.08},{"index":23,"x0":450,"y0":289,"score0":0.08,"x1":448,"y1":323,"score1":0.02},{"index":23,"x0":429,"y0":279,"score0":0.38,"x1":427,"y1":276,"score1":0.37},{"index":23,"x0":423,"y0":274,"score0":0.26,"x1":427,"y1":276,"score1":0.37},{"index":23,"x0":421,"y0":318,"score0":0.1,"x1":415,"y1":333,"score1":0.08},{"index":23,"x0":424,"y0":336,"score0":0.04,"x1":422,"y1":370,"score1":0.02},{"index":23,"x0":422,"y0":370,"score0":0.02,"x1":432,"y1":401,"score1":0.03},{"index":23,"x0":424,"y0":293,"score0":0.08,"x1":421,"y1":318,"score1":0.1},{"index":24,"x0":282,"y0":419,"score0":0.25,"x1":263,"y1":420,"score1":0.5},{"index":24,"x0":276,"y0":475,"score0":0.02,"x1":340,"y1":471,"score1":0.07},{"index":24,"x0":263,"y0":420,"score0":0.5,"x1":255,"y1":425,"score1":0.35},{"index":24,"x0":281,"y0":491,"score0":0.02,"x1":249,"y1":483,"score1":0.02},{"index":24,"x0":281,"y0":491,"score0":0.02,"x1":307,"y1":491,"score1":0.02},{"index":24,"x0":307,"y0":491,"score0":0.02,"x1":342,"y1":473,"score1":0.05},{"index":24,"x0":302,"y0":446,"score0":0.06,"x1":276,"y1":473,"score1":0.02},{"index":24,"x0":302,"y0":446,"score0":0.06,"x1":276,"y1":475,"score1":0.02},{"index":24,"x0":255,"y0":425,"score0":0.35,"x1":254,"y1":418,"score1":0.41},{"index":24,"x0":251,"y0":413,"score0":0.1,"x1":254,"y1":418,"score1":0.41},{"index":24,"x0":235,"y0":460,"score0":0.05,"x1":235,"y1":444,"score1":0.12},{"index":24,"x0":249,"y0":483,"score0":0.02,"x1":267,"y1":491,"score1":0.01},{"index":24,"x0":267,"y0":491,"score0":0.01,"x1":344,"y1":475,"score1":0.02},{"index":24,"x0":276,"y0":473,"score0":0.02,"x1":235,"y1":460,"score1":0.05},{"index":25,"x0":457,"y0":173,"score0":0.12,"x1":453,"y1":172,"score1":0.11},{"index":25,"x0":460,"y0":197,"score0":0.04,"x1":455,"y1":199,"score1":0.02},{"index":25,"x0":453,"y0":172,"score0":0.11,"x1":451,"y1":173,"score1":0.11},{"index":25,"x0":453,"y0":205,"score0":0.02,"x1":444,"y1":202,"score1":0.02},{"index":25,"x0":453,"y0":205,"score0":0.02,"x1":448,"y1":218,"score1":0.01},{"index":25,"x0":448,"y0":218,"score0":0.01,"x1":441,"y1":246,"score1":0.01},{"index":25,"x0":459,"y0":184,"score0":0.05,"x1":444,"y1":184,"score1":0.06},{"index":25,"x0":459,"y0":184,"score0":0.05,"x1":460,"y1":197,"score1":0.04},{"index":25,"x0":451,"y0":173,"score0":0.11,"x1":449,"y1":172,"score1":0.11},{"index":25,"x0":445,"y0":173,"score0":0.1,"x1":449,"y1":172,"score1":0.11},{"index":25,"x0":429,"y0":221,"score0":0.05,"x1":448,"y1":196,"score1":0.01},{"index":25,"x0":444,"y0":202,"score0":0.02,"x1":441,"y1":219,"score1":0.01},{"index":25,"x0":441,"y0":219,"score0":0.01,"x1":437,"y1":238,"score1":0.01},{"index":25,"x0":444,"y0":184,"score0":0.06,"x1":429,"y1":221,"score1":0.05},{"index":26,"x0":473,"y0":184,"score0":0.24,"x1":467,"y1":180,"score1":0.22},{"index":26,"x0":485,"y0":201,"score0":0.08,"x1":487,"y1":204,"score1":0.04},{"index":26,"x0":467,"y0":180,"score0":0.22,"x1":463,"y1":182,"score1":0.26},{"index":26,"x0":470,"y0":224,"score0":0.04,"x1":460,"y1":223,"score1":0.04},{"index":26,"x0":470,"y0":224,"score0":0.04,"x1":474,"y1":260,"score1":0.02},{"index":26,"x0":474,"y0":260,"score0":0.02,"x1":443,"y1":252,"score1":0.02},{"index":26,"x0":473,"y0":193,"score0":0.11,"x1":460,"y1":194,"score1":0.08},{"index":26,"x0":473,"y0":193,"score0":0.11,"x1":485,"y1":201,"score1":0.08},{"index":26,"x0":463,"y0":182,"score0":0.26,"x1":462,"y1":180,"score1":0.22},{"index":26,"x0":459,"y0":181,"score0":0.11,"x1":462,"y1":180,"score1":0.22},{"index":26,"x0":460,"y0":196,"score0":0.02,"x1":446,"y1":247,"score1":0.03},{"index":26,"x0":460,"y0":223,"score0":0.04,"x1":448,"y1":242,"score1":0.06},{"index":26,"x0":448,"y0":242,"score0":0.06,"x1":444,"y1":251,"score1":0.02},{"index":26,"x0":460,"y0":194,"score0":0.08,"x1":460,"y1":196,"score1":0.02},{"index":27,"x0":707,"y0":218,"score0":0.21,"x1":701,"y1":218,"score1":0.2},{"index":27,"x0":707,"y0":254,"score0":0.03,"x1":696,"y1":259,"score1":0.01},{"index":27,"x0":701,"y0":218,"score0":0.2,"x1":697,"y1":220,"score1":0.18},{"index":27,"x0":698,"y0":268,"score0":0.04,"x1":688,"y1":265,"score1":0.04},{"index":27,"x0":698,"y0":268,"score0":0.04,"x1":693,"y1":297,"score1":0.04},{"index":27,"x0":693,"y0":297,"score0":0.04,"x1":695,"y1":323,"score1":0.09},{"index":27,"x0":708,"y0":230,"score0":0.06,"x1":694,"y1":231,"score1":0.06},{"index":27,"x0":708,"y0":230,"score0":0.06,"x1":707,"y1":254,"score1":0.03},{"index":27,"x0":697,"y0":220,"score0":0.18,"x1":696,"y1":217,"score1":0.27},{"index":27,"x0":694,"y0":217,"score0":0.17,"x1":696,"y1":217,"score1":0.27},{"index":27,"x0":689,"y0":250,"score0":0.03,"x1":684,"y1":259,"score1":0.02},{"index":27,"x0":688,"y0":265,"score0":0.04,"x1":667,"y1":278,"score1":0.03},{"index":27,"x0":667,"y0":278,"score0":0.03,"x1":690,"y1":317,"score1":0.03},{"index":27,"x0":694,"y0":231,"score0":0.06,"x1":689,"y1":250,"score1":0.03},{"index":28,"x0":800,"y0":246,"score0":0.22,"x1":794,"y1":243,"score1":0.4},{"index":28,"x0":814,"y0":282,"score0":0.11,"x1":804,"y1":294,"score1":0.03},{"index":28,"x0":794,"y0":243,"score0":0.4,"x1":790,"y1":247,"score1":0.3},{"index":28,"x0":793,"y0":301,"score0":0.03,"x1":777,"y1":298,"score1":0.05},{"index":28,"x0":793,"y0":301,"score0":0.03,"x1":796,"y1":337,"score1":0.04},{"index":28,"x0":796,"y0":337,"score0":0.04,"x1":814,"y1":337,"score1":0.02},{"index":28,"x0":802,"y0":264,"score0":0.09,"x1":783,"y1":256,"score1":0.1},{"index":28,"x0":802,"y0":264,"score0":0.09,"x1":814,"y1":282,"score1":0.11},{"index":28,"x0":790,"y0":247,"score0":0.3,"x1":788,"y1":243,"score1":0.42},{"index":28,"x0":784,"y0":243,"score0":0.28,"x1":788,"y1":243,"score1":0.42},{"index":28,"x0":777,"y0":277,"score0":0.02,"x1":772,"y1":303,"score1":0.01},{"index":28,"x0":777,"y0":298,"score0":0.05,"x1":777,"y1":329,"score1":0.02},{"index":28,"x0":777,"y0":329,"score0":0.02,"x1":777,"y1":337,"score1":0.03},{"index":28,"x0":783,"y0":256,"score0":0.1,"x1":777,"y1":277,"score1":0.02},{"index":29,"x0":239,"y0":198,"score0":0.27,"x1":236,"y1":196,"score1":0.3},{"index":29,"x0":268,"y0":216,"score0":0.05,"x1":268,"y1":215,"score1":0.1},{"index":29,"x0":236,"y0":196,"score0":0.3,"x1":235,"y1":198,"score1":0.22},{"index":29,"x0":241,"y0":238,"score0":0.08,"x1":225,"y1":238,"score1":0.07},{"index":29,"x0":241,"y0":238,"score0":0.08,"x1":239,"y1":268,"score1":0.02},{"index":29,"x0":239,"y0":268,"score0":0.02,"x1":241,"y1":301,"score1":0.03},{"index":29,"x0":245,"y0":209,"score0":0.18,"x1":223,"y1":209,"score1":0.07},{"index":29,"x0":245,"y0":209,"score0":0.18,"x1":268,"y1":216,"score1":0.05},{"index":29,"x0":235,"y0":198,"score0":0.22,"x1":232,"y1":196,"score1":0.25},{"index":29,"x0":227,"y0":198,"score0":0.25,"x1":232,"y1":196,"score1":0.25},{"index":29,"x0":215,"y0":204,"score0":0.06,"x1":215,"y1":243,"score1":0.02},{"index":29,"x0":225,"y0":238,"score0":0.07,"x1":226,"y1":267,"score1":0.04},{"index":29,"x0":226,"y0":267,"score0":0.04,"x1":224,"y1":292,"score1":0.05},{"index":29,"x0":223,"y0":209,"score0":0.07,"x1":215,"y1":204,"score1":0.06},{"index":30,"x0":659,"y0":200,"score0":0.22,"x1":656,"y1":200,"score1":0.2},{"index":30,"x0":678,"y0":217,"score0":0.13,"x1":674,"y1":200,"score1":0.01},{"index":30,"x0":656,"y0":200,"score0":0.2,"x1":654,"y1":202,"score1":0.23},{"index":30,"x0":662,"y0":249,"score0":0.03,"x1":647,"y1":248,"score1":0.03},{"index":30,"x0":662,"y0":249,"score0":0.03,"x1":652,"y1":265,"score1":0.02},{"index":30,"x0":652,"y0":265,"score0":0.02,"x1":657,"y1":302,"score1":0.09},{"index":30,"x0":663,"y0":208,"score0":0.12,"x1":643,"y1":205,"score1":0.09},{"index":30,"x0":663,"y0":208,"score0":0.12,"x1":678,"y1":217,"score1":0.13},{"index":30,"x0":654,"y0":202,"score0":0.23,"x1":652,"y1":200,"score1":0.18},{"index":30,"x0":648,"y0":199,"score0":0.24,"x1":652,"y1":200,"score1":0.18},{"index":30,"x0":631,"y0":197,"score0":0.12,"x1":622,"y1":187,"score1":0.02},{"index":30,"x0":647,"y0":248,"score0":0.03,"x1":637,"y1":266,"score1":0.08},{"index":30,"x0":637,"y0":266,"score0":0.08,"x1":633,"y1":291,"score1":0.05},{"index":30,"x0":643,"y0":205,"score0":0.09,"x1":631,"y1":197,"score1":0.12},{"index":31,"x0":202,"y0":188,"score0":0.06,"x1":199,"y1":188,"score1":0.08},{"index":31,"x0":212,"y0":198,"score0":0.02,"x1":209,"y1":207,"score1":0.01},{"index":31,"x0":199,"y0":188,"score0":0.08,"x1":196,"y1":191,"score1":0.07},{"index":31,"x0":208,"y0":233,"score0":0.01,"x1":194,"y1":233,"score1":0.01},{"index":31,"x0":208,"y0":233,"score0":0.01,"x1":210,"y1":238,"score1":0.01},{"index":31,"x0":210,"y0":238,"score0":0.01,"x1":203,"y1":238,"score1":0.01},{"index":31,"x0":206,"y0":198,"score0":0.02,"x1":190,"y1":200,"score1":0.03},{"index":31,"x0":206,"y0":198,"score0":0.02,"x1":212,"y1":198,"score1":0.02},{"index":31,"x0":196,"y0":191,"score0":0.07,"x1":194,"y1":188,"score1":0.08},{"index":31,"x0":191,"y0":189,"score0":0.07,"x1":194,"y1":188,"score1":0.08},{"index":31,"x0":186,"y0":212,"score0":0.02,"x1":189,"y1":208,"score1":0.01},{"index":31,"x0":194,"y0":233,"score0":0.01,"x1":194,"y1":235,"score1":0.01},{"index":31,"x0":194,"y0":235,"score0":0.01,"x1":188,"y1":238,"score1":0.01},{"index":31,"x0":190,"y0":200,"score0":0.03,"x1":186,"y1":212,"score1":0.02},{"index":32,"x0":148,"y0":123,"score0":0.06,"x1":146,"y1":122,"score1":0.06},{"index":32,"x0":159,"y0":151,"score0":0.02,"x1":162,"y1":164,"score1":0.04},{"index":32,"x0":146,"y0":122,"score0":0.06,"x1":144,"y1":124,"score1":0.05},{"index":32,"x0":150,"y0":159,"score0":0.03,"x1":138,"y1":157,"score1":0.02},{"index":32,"x0":150,"y0":159,"score0":0.03,"x1":149,"y1":176,"score1":0.03},{"index":32,"x0":149,"y0":176,"score0":0.03,"x1":149,"y1":176,"score1":0.01},{"index":32,"x0":153,"y0":134,"score0":0.05,"x1":137,"y1":134,"score1":0.06},{"index":32,"x0":153,"y0":134,"score0":0.05,"x1":159,"y1":151,"score1":0.02},{"index":32,"x0":144,"y0":124,"score0":0.05,"x1":141,"y1":122,"score1":0.06},{"index":32,"x0":139,"y0":124,"score0":0.07,"x1":141,"y1":122,"score1":0.06},{"index":32,"x0":134,"y0":128,"score0":0.02,"x1":139,"y1":125,"score1":0.01},{"index":32,"x0":138,"y0":157,"score0":0.02,"x1":139,"y1":176,"score1":0.02},{"index":32,"x0":139,"y0":176,"score0":0.02,"x1":142,"y1":176,"score1":0.01},{"index":32,"x0":137,"y0":134,"score0":0.06,"x1":134,"y1":128,"score1":0.02},{"index":33,"x0":250,"y0":130,"score0":0.06,"x1":245,"y1":130,"score1":0.08},{"index":33,"x0":262,"y0":146,"score0":0.03,"x1":263,"y1":149,"score1":0.01},{"index":33,"x0":245,"y0":130,"score0":0.08,"x1":244,"y1":133,"score1":0.09},{"index":33,"x0":251,"y0":163,"score0":0.04,"x1":243,"y1":163,"score1":0.04},{"index":33,"x0":251,"y0":163,"score0":0.04,"x1":250,"y1":183,"score1":0.04},{"index":33,"x0":250,"y0":183,"score0":0.04,"x1":251,"y1":197,"score1":0.03},{"index":33,"x0":255,"y0":140,"score0":0.04,"x1":243,"y1":140,"score1":0.05},{"index":33,"x0":255,"y0":140,"score0":0.04,"x1":262,"y1":146,"score1":0.03},{"index":33,"x0":244,"y0":133,"score0":0.09,"x1":242,"y1":130,"score1":0.1},{"index":33,"x0":240,"y0":132,"score0":0.06,"x1":242,"y1":130,"score1":0.1},{"index":33,"x0":240,"y0":154,"score0":0.01,"x1":240,"y1":163,"score1":0.02},{"index":33,"x0":243,"y0":163,"score0":0.04,"x1":242,"y1":183,"score1":0.04},{"index":33,"x0":242,"y0":183,"score0":0.04,"x1":243,"y1":197,"score1":0.03},{"index":33,"x0":243,"y0":140,"score0":0.05,"x1":240,"y1":154,"score1":0.01},{"index":34,"x0":927,"y0":250,"score0":0.17,"x1":921,"y1":248,"score1":0.25},{"index":34,"x0":945,"y0":295,"score0":0.02,"x1":935,"y1":287,"score1":0.01},{"index":34,"x0":921,"y0":248,"score0":0.25,"x1":917,"y1":250,"score1":0.21},{"index":34,"x0":929,"y0":293,"score0":0.01,"x1":905,"y1":295,"score1":0.01},{"index":34,"x0":929,"y0":293,"score0":0.01,"x1":945,"y1":295,"score1":0.01},{"index":34,"x0":945,"y0":295,"score0":0.01,"x1":945,"y1":295,"score1":0.01},{"index":34,"x0":932,"y0":268,"score0":0.02,"x1":894,"y1":266,"score1":0.02},{"index":34,"x0":932,"y0":268,"score0":0.02,"x1":945,"y1":295,"score1":0.02},{"index":34,"x0":917,"y0":250,"score0":0.21,"x1":916,"y1":247,"score1":0.29},{"index":34,"x0":910,"y0":247,"score0":0.23,"x1":916,"y1":247,"score1":0.29},{"index":34,"x0":896,"y0":292,"score0":0.02,"x1":886,"y1":260,"score1":0.04},{"index":34,"x0":905,"y0":295,"score0":0.01,"x1":896,"y1":292,"score1":0.02},{"index":34,"x0":896,"y0":292,"score0":0.02,"x1":896,"y1":292,"score1":0.03},{"index":34,"x0":894,"y0":266,"score0":0.02,"x1":896,"y1":292,"score1":0.02}],"kpnt":[{"score":0.83,"x":687,"y":395},{"score":0.76,"x":692,"y":391},{"score":1.16,"x":684,"y":389},{"score":0.63,"x":704,"y":393},{"score":0.38,"x":679,"y":390},{"score":0.17,"x":710,"y":419},{"score":0.14,"x":677,"y":405},{"score":0.24,"x":729,"y":438},{"score":0.04,"x":672,"y":435},{"score":0.22,"x":754,"y":453},{"score":0.02,"x":664,"y":467},{"score":0.1,"x":690,"y":482},{"score":0.12,"x":669,"y":472},{"score":0.09,"x":682,"y":529},{"score":0.15,"x":630,"y":475},{"score":0.04,"x":651,"y":515},{"score":0.07,"x":651,"y":514},{"score":0.46,"x":543,"y":362},{"score":0.55,"x":548,"y":360},{"score":0.49,"x":540,"y":357},{"score":0.41,"x":556,"y":360},{"score":0.52,"x":535,"y":349},{"score":0.21,"x":555,"y":381},{"score":0.19,"x":523,"y":353},{"score":0.15,"x":573,"y":409},{"score":0.11,"x":498,"y":328},{"score":0.22,"x":585,"y":423},{"score":0.05,"x":497,"y":328},{"score":0.14,"x":535,"y":434},{"score":0.11,"x":519,"y":430},{"score":0.14,"x":496,"y":458},{"score":0.06,"x":526,"y":472},{"score":0.2,"x":535,"y":515},{"score":0.13,"x":490,"y":496},{"score":0.31,"x":651,"y":355},{"score":0.27,"x":655,"y":351},{"score":0.24,"x":645,"y":351},{"score":0.29,"x":663,"y":351},{"score":0.35,"x":638,"y":350},{"score":0.08,"x":666,"y":384},{"score":0.13,"x":636,"y":359},{"score":0.04,"x":673,"y":420},{"score":0.11,"x":619,"y":347},{"score":0.01,"x":671,"y":444},{"score":0.06,"x":603,"y":332},{"score":0.03,"x":649,"y":432},{"score":0.05,"x":626,"y":429},{"score":0.05,"x":610,"y":447},{"score":0.03,"x":606,"y":448},{"score":0.02,"x":612,"y":483},{"score":0.02,"x":610,"y":483},{"score":0.5,"x":408,"y":511},{"score":0.43,"x":411,"y":505},{"score":0.39,"x":408,"y":504},{"score":0.41,"x":431,"y":504},{"score":0.16,"x":431,"y":503},{"score":0.04,"x":441,"y":534},{"score":0.04,"x":423,"y":526},{"score":0.07,"x":483,"y":537},{"score":0.04,"x":391,"y":504},{"score":0.01,"x":410,"y":612},{"score":0.03,"x":378,"y":518},{"score":0.04,"x":443,"y":635},{"score":0.05,"x":417,"y":631},{"score":0.02,"x":447,"y":709},{"score":0.02,"x":401,"y":711},{"score":0.03,"x":449,"y":722},{"score":0.02,"x":389,"y":722},{"score":0.24,"x":59,"y":342},{"score":0.37,"x":63,"y":337},{"score":0.37,"x":55,"y":338},{"score":0.18,"x":75,"y":336},{"score":0.18,"x":52,"y":338},{"score":0.09,"x":84,"y":355},{"score":0.05,"x":56,"y":358},{"score":0.07,"x":84,"y":394},{"score":0.07,"x":47,"y":403},{"score":0.02,"x":82,"y":382},{"score":0.07,"x":50,"y":360},{"score":0.02,"x":82,"y":416},{"score":0.05,"x":63,"y":414},{"score":0.02,"x":88,"y":461},{"score":0.02,"x":51,"y":455},{"score":0.03,"x":103,"y":469},{"score":0.02,"x":73,"y":469},{"score":0.1,"x":971,"y":359},{"score":0.09,"x":974,"y":355},{"score":0.09,"x":973,"y":355},{"score":0.13,"x":983,"y":359},{"score":0.02,"x":981,"y":357},{"score":0.08,"x":989,"y":390},{"score":0.05,"x":976,"y":376},{"score":0.15,"x":987,"y":428},{"score":0.03,"x":965,"y":401},{"score":0.12,"x":971,"y":455},{"score":0.03,"x":956,"y":413},{"score":0.02,"x":973,"y":446},{"score":0.03,"x":961,"y":439},{"score":0.04,"x":973,"y":502},{"score":0.03,"x":961,"y":492},{"score":0.09,"x":974,"y":552},{"score":0.02,"x":965,"y":537},{"score":0.88,"x":310,"y":530},{"score":0.55,"x":317,"y":524},{"score":0.73,"x":306,"y":522},{"score":0.24,"x":334,"y":521},{"score":0.07,"x":304,"y":519},{"score":0.09,"x":347,"y":556},{"score":0.05,"x":316,"y":545},{"score":0.09,"x":360,"y":585},{"score":0.02,"x":295,"y":583},{"score":0.06,"x":373,"y":614},{"score":0.07,"x":295,"y":590},{"score":0.03,"x":345,"y":639},{"score":0.03,"x":314,"y":637},{"score":0.03,"x":360,"y":693},{"score":0.01,"x":326,"y":702},{"score":0.03,"x":296,"y":708},{"score":0.02,"x":295,"y":709},{"score":0.69,"x":836,"y":362},{"score":0.74,"x":841,"y":361},{"score":0.9,"x":835,"y":357},{"score":0.56,"x":849,"y":362},{"score":0.3,"x":832,"y":353},{"score":0.21,"x":853,"y":381},{"score":0.11,"x":824,"y":361},{"score":0.16,"x":875,"y":392},{"score":0.05,"x":791,"y":343},{"score":0.1,"x":898,"y":416},{"score":0.07,"x":795,"y":347},{"score":0.07,"x":838,"y":426},{"score":0.12,"x":817,"y":420},{"score":0.14,"x":792,"y":454},{"score":0.05,"x":814,"y":457},{"score":0.14,"x":762,"y":481},{"score":0.13,"x":826,"y":506},{"score":0.5,"x":137,"y":561},{"score":0.42,"x":140,"y":553},{"score":0.38,"x":138,"y":553},{"score":0.18,"x":157,"y":554},{"score":0.06,"x":157,"y":553},{"score":0.09,"x":182,"y":589},{"score":0.04,"x":148,"y":579},{"score":0.08,"x":194,"y":644},{"score":0.03,"x":139,"y":622},{"score":0.03,"x":166,"y":680},{"score":0.02,"x":221,"y":722},{"score":0.03,"x":179,"y":701},{"score":0.01,"x":161,"y":701},{"score":0.01,"x":194,"y":711},{"score":0.02,"x":160,"y":722},{"score":0.05,"x":221,"y":722},{"score":0.02,"x":157,"y":722},{"score":0.45,"x":317,"y":245},{"score":0.36,"x":321,"y":243},{"score":0.4,"x":316,"y":241},{"score":0.25,"x":332,"y":243},{"score":0.06,"x":317,"y":238},{"score":0.19,"x":335,"y":258},{"score":0.15,"x":316,"y":253},{"score":0.07,"x":349,"y":266},{"score":0.05,"x":308,"y":236},{"score":0.1,"x":363,"y":271},{"score":0.04,"x":363,"y":271},{"score":0.08,"x":324,"y":299},{"score":0.12,"x":312,"y":295},{"score":0.07,"x":316,"y":330},{"score":0.07,"x":291,"y":308},{"score":0.12,"x":327,"y":362},{"score":0.21,"x":287,"y":340},{"score":0.66,"x":178,"y":337},{"score":0.58,"x":182,"y":331},{"score":0.58,"x":175,"y":333},{"score":0.37,"x":194,"y":329},{"score":0.25,"x":172,"y":334},{"score":0.13,"x":197,"y":350},{"score":0.05,"x":183,"y":348},{"score":0.03,"x":200,"y":365},{"score":0.03,"x":174,"y":326},{"score":0.03,"x":195,"y":396},{"score":0.02,"x":194,"y":324},{"score":0.05,"x":185,"y":401},{"score":0.04,"x":175,"y":401},{"score":0.07,"x":146,"y":428},{"score":0.03,"x":144,"y":430},{"score":0.07,"x":192,"y":477},{"score":0.07,"x":137,"y":473},{"score":0.68,"x":736,"y":318},{"score":0.57,"x":741,"y":313},{"score":0.64,"x":733,"y":313},{"score":0.4,"x":750,"y":314},{"score":0.38,"x":729,"y":315},{"score":0.13,"x":759,"y":335},{"score":0.13,"x":728,"y":330},{"score":0.12,"x":784,"y":341},{"score":0.03,"x":722,"y":364},{"score":0.08,"x":798,"y":346},{"score":0.04,"x":720,"y":385},{"score":0.05,"x":748,"y":395},{"score":0.06,"x":725,"y":390},{"score":0.05,"x":742,"y":445},{"score":0.02,"x":724,"y":442},{"score":0.03,"x":745,"y":452},{"score":0.03,"x":752,"y":452},{"score":0.63,"x":57,"y":487},{"score":0.64,"x":63,"y":482},{"score":0.59,"x":53,"y":482},{"score":0.5,"x":81,"y":483},{"score":0.22,"x":82,"y":482},{"score":0.12,"x":96,"y":514},{"score":0.07,"x":73,"y":507},{"score":0.04,"x":113,"y":529},{"score":0.05,"x":59,"y":545},{"score":0.06,"x":126,"y":506},{"score":0.02,"x":52,"y":526},{"score":0.06,"x":94,"y":590},{"score":0.04,"x":72,"y":579},{"score":0.05,"x":92,"y":652},{"score":0.08,"x":87,"y":650},{"score":0.09,"x":103,"y":716},{"score":0.07,"x":100,"y":705},{"score":1.09,"x":915,"y":281},{"score":0.69,"x":918,"y":277},{"score":0.74,"x":911,"y":277},{"score":0.44,"x":921,"y":278},{"score":0.7,"x":903,"y":278},{"score":0.18,"x":925,"y":297},{"score":0.17,"x":896,"y":296},{"score":0.17,"x":946,"y":297},{"score":0.14,"x":882,"y":273},{"score":0.07,"x":959,"y":304},{"score":0.23,"x":889,"y":257},{"score":0.08,"x":915,"y":345},{"score":0.08,"x":895,"y":343},{"score":0.09,"x":916,"y":380},{"score":0.11,"x":895,"y":380},{"score":0.03,"x":899,"y":411},{"score":0.16,"x":898,"y":411},{"score":0.42,"x":383,"y":225},{"score":0.4,"x":386,"y":223},{"score":0.49,"x":381,"y":222},{"score":0.38,"x":392,"y":223},{"score":0.31,"x":378,"y":223},{"score":0.12,"x":397,"y":237},{"score":0.15,"x":378,"y":235},{"score":0.09,"x":413,"y":251},{"score":0.06,"x":366,"y":248},{"score":0.05,"x":402,"y":271},{"score":0.01,"x":349,"y":261},{"score":0.07,"x":391,"y":282},{"score":0.1,"x":375,"y":279},{"score":0.03,"x":398,"y":319},{"score":0.15,"x":354,"y":292},{"score":0.02,"x":356,"y":323},{"score":0.07,"x":356,"y":321},{"score":0.12,"x":94,"y":317},{"score":0.14,"x":96,"y":312},{"score":0.13,"x":89,"y":316},{"score":0.15,"x":105,"y":309},{"score":0.07,"x":87,"y":316},{"score":0.12,"x":117,"y":325},{"score":0.07,"x":92,"y":331},{"score":0.07,"x":130,"y":330},{"score":0.03,"x":87,"y":350},{"score":0.08,"x":139,"y":333},{"score":0.01,"x":87,"y":346},{"score":0.07,"x":115,"y":369},{"score":0.04,"x":97,"y":369},{"score":0.07,"x":118,"y":408},{"score":0.03,"x":96,"y":411},{"score":0.14,"x":120,"y":444},{"score":0.02,"x":94,"y":444},{"score":1.18,"x":286,"y":468},{"score":0.89,"x":291,"y":461},{"score":0.77,"x":279,"y":463},{"score":0.4,"x":300,"y":456},{"score":0.3,"x":270,"y":460},{"score":0.04,"x":317,"y":478},{"score":0.09,"x":274,"y":478},{"score":0.02,"x":294,"y":534},{"score":0.05,"x":237,"y":456},{"score":0.02,"x":288,"y":500},{"score":0.09,"x":235,"y":444},{"score":0.01,"x":301,"y":541},{"score":0.02,"x":282,"y":539},{"score":0.01,"x":289,"y":573},{"score":0.07,"x":239,"y":556},{"score":0.01,"x":239,"y":629},{"score":0.05,"x":224,"y":617},{"score":0.14,"x":143,"y":210},{"score":0.12,"x":145,"y":208},{"score":0.16,"x":141,"y":208},{"score":0.18,"x":152,"y":208},{"score":0.13,"x":138,"y":206},{"score":0.05,"x":155,"y":221},{"score":0.07,"x":140,"y":221},{"score":0.02,"x":156,"y":245},{"score":0.03,"x":133,"y":241},{"score":0.01,"x":156,"y":220},{"score":0.05,"x":129,"y":251},{"score":0.03,"x":152,"y":254},{"score":0.04,"x":141,"y":253},{"score":0.1,"x":124,"y":267},{"score":0.05,"x":124,"y":265},{"score":0.07,"x":122,"y":292},{"score":0.04,"x":123,"y":290},{"score":0.12,"x":87,"y":199},{"score":0.15,"x":89,"y":197},{"score":0.05,"x":87,"y":197},{"score":0.1,"x":95,"y":195},{"score":0.06,"x":107,"y":188},{"score":0.04,"x":106,"y":206},{"score":0.03,"x":90,"y":207},{"score":0.02,"x":114,"y":220},{"score":0.02,"x":113,"y":219},{"score":0.01,"x":112,"y":225},{"score":0.01,"x":117,"y":230},{"score":0.03,"x":107,"y":241},{"score":0.05,"x":94,"y":241},{"score":0.03,"x":107,"y":268},{"score":0.03,"x":92,"y":273},{"score":0.04,"x":109,"y":289},{"score":0.02,"x":92,"y":294},{"score":0.34,"x":607,"y":318},{"score":0.33,"x":611,"y":313},{"score":0.32,"x":603,"y":314},{"score":0.27,"x":618,"y":315},{"score":0.12,"x":599,"y":315},{"score":0.06,"x":628,"y":334},{"score":0.06,"x":600,"y":335},{"score":0.05,"x":635,"y":359},{"score":0.01,"x":583,"y":315},{"score":0.11,"x":596,"y":315},{"score":0.01,"x":594,"y":313},{"score":0.01,"x":614,"y":387},{"score":0.01,"x":594,"y":392},{"score":0.01,"x":609,"y":427},{"score":0.02,"x":574,"y":433},{"score":0.01,"x":608,"y":423},{"score":0.02,"x":574,"y":433},{"score":0.15,"x":179,"y":229},{"score":0.16,"x":182,"y":225},{"score":0.19,"x":177,"y":226},{"score":0.16,"x":190,"y":227},{"score":0.13,"x":174,"y":228},{"score":0.07,"x":197,"y":243},{"score":0.04,"x":183,"y":241},{"score":0.08,"x":196,"y":262},{"score":0.02,"x":170,"y":250},{"score":0.12,"x":194,"y":280},{"score":0.02,"x":166,"y":247},{"score":0.02,"x":188,"y":275},{"score":0.02,"x":180,"y":272},{"score":0.01,"x":181,"y":305},{"score":0.01,"x":171,"y":303},{"score":0.02,"x":196,"y":322},{"score":0.01,"x":170,"y":305},{"score":0.31,"x":472,"y":268},{"score":0.37,"x":477,"y":264},{"score":0.37,"x":470,"y":265},{"score":0.36,"x":483,"y":267},{"score":0.3,"x":466,"y":267},{"score":0.08,"x":489,"y":281},{"score":0.08,"x":462,"y":282},{"score":0.04,"x":498,"y":289},{"score":0.02,"x":454,"y":304},{"score":0.05,"x":513,"y":297},{"score":0.01,"x":458,"y":301},{"score":0.03,"x":484,"y":322},{"score":0.02,"x":464,"y":319},{"score":0.02,"x":475,"y":353},{"score":0.06,"x":467,"y":352},{"score":0.07,"x":476,"y":384},{"score":0.13,"x":475,"y":383},{"score":0.12,"x":510,"y":164},{"score":0.11,"x":512,"y":161},{"score":0.14,"x":508,"y":161},{"score":0.14,"x":515,"y":165},{"score":0.15,"x":504,"y":163},{"score":0.08,"x":516,"y":176},{"score":0.08,"x":502,"y":174},{"score":0.11,"x":529,"y":178},{"score":0.06,"x":498,"y":188},{"score":0.12,"x":529,"y":178},{"score":0.04,"x":496,"y":196},{"score":0.05,"x":512,"y":201},{"score":0.05,"x":501,"y":200},{"score":0.03,"x":514,"y":220},{"score":0.02,"x":501,"y":217},{"score":0.03,"x":515,"y":230},{"score":0.01,"x":509,"y":226},{"score":0.38,"x":429,"y":279},{"score":0.34,"x":433,"y":276},{"score":0.37,"x":427,"y":276},{"score":0.33,"x":442,"y":274},{"score":0.26,"x":423,"y":274},{"score":0.08,"x":450,"y":289},{"score":0.08,"x":424,"y":293},{"score":0.02,"x":448,"y":323},{"score":0.1,"x":421,"y":318},{"score":0.03,"x":450,"y":323},{"score":0.08,"x":415,"y":333},{"score":0.03,"x":440,"y":337},{"score":0.04,"x":424,"y":336},{"score":0.02,"x":426,"y":367},{"score":0.02,"x":422,"y":370},{"score":0.05,"x":433,"y":401},{"score":0.03,"x":432,"y":401},{"score":0.35,"x":255,"y":425},{"score":0.5,"x":263,"y":420},{"score":0.41,"x":254,"y":418},{"score":0.25,"x":282,"y":419},{"score":0.1,"x":251,"y":413},{"score":0.06,"x":302,"y":446},{"score":0.02,"x":276,"y":473},{"score":0.02,"x":276,"y":475},{"score":0.05,"x":235,"y":460},{"score":0.07,"x":340,"y":471},{"score":0.12,"x":235,"y":444},{"score":0.02,"x":281,"y":491},{"score":0.02,"x":249,"y":483},{"score":0.02,"x":307,"y":491},{"score":0.01,"x":267,"y":491},{"score":0.05,"x":342,"y":473},{"score":0.02,"x":344,"y":475},{"score":0.11,"x":451,"y":173},{"score":0.11,"x":453,"y":172},{"score":0.11,"x":449,"y":172},{"score":0.12,"x":457,"y":173},{"score":0.1,"x":445,"y":173},{"score":0.05,"x":459,"y":184},{"score":0.06,"x":444,"y":184},{"score":0.04,"x":460,"y":197},{"score":0.05,"x":429,"y":221},{"score":0.02,"x":455,"y":199},{"score":0.01,"x":448,"y":196},{"score":0.02,"x":453,"y":205},{"score":0.02,"x":444,"y":202},{"score":0.01,"x":448,"y":218},{"score":0.01,"x":441,"y":219},{"score":0.01,"x":441,"y":246},{"score":0.01,"x":437,"y":238},{"score":0.26,"x":463,"y":182},{"score":0.22,"x":467,"y":180},{"score":0.22,"x":462,"y":180},{"score":0.24,"x":473,"y":184},{"score":0.11,"x":459,"y":181},{"score":0.11,"x":473,"y":193},{"score":0.08,"x":460,"y":194},{"score":0.08,"x":485,"y":201},{"score":0.02,"x":460,"y":196},{"score":0.04,"x":487,"y":204},{"score":0.03,"x":446,"y":247},{"score":0.04,"x":470,"y":224},{"score":0.04,"x":460,"y":223},{"score":0.02,"x":474,"y":260},{"score":0.06,"x":448,"y":242},{"score":0.02,"x":443,"y":252},{"score":0.02,"x":444,"y":251},{"score":0.18,"x":697,"y":220},{"score":0.2,"x":701,"y":218},{"score":0.27,"x":696,"y":217},{"score":0.21,"x":707,"y":218},{"score":0.17,"x":694,"y":217},{"score":0.06,"x":708,"y":230},{"score":0.06,"x":694,"y":231},{"score":0.03,"x":707,"y":254},{"score":0.03,"x":689,"y":250},{"score":0.01,"x":696,"y":259},{"score":0.02,"x":684,"y":259},{"score":0.04,"x":698,"y":268},{"score":0.04,"x":688,"y":265},{"score":0.04,"x":693,"y":297},{"score":0.03,"x":667,"y":278},{"score":0.09,"x":695,"y":323},{"score":0.03,"x":690,"y":317},{"score":0.3,"x":790,"y":247},{"score":0.4,"x":794,"y":243},{"score":0.42,"x":788,"y":243},{"score":0.22,"x":800,"y":246},{"score":0.28,"x":784,"y":243},{"score":0.09,"x":802,"y":264},{"score":0.1,"x":783,"y":256},{"score":0.11,"x":814,"y":282},{"score":0.02,"x":777,"y":277},{"score":0.03,"x":804,"y":294},{"score":0.01,"x":772,"y":303},{"score":0.03,"x":793,"y":301},{"score":0.05,"x":777,"y":298},{"score":0.04,"x":796,"y":337},{"score":0.02,"x":777,"y":329},{"score":0.02,"x":814,"y":337},{"score":0.03,"x":777,"y":337},{"score":0.22,"x":235,"y":198},{"score":0.3,"x":236,"y":196},{"score":0.25,"x":232,"y":196},{"score":0.27,"x":239,"y":198},{"score":0.25,"x":227,"y":198},{"score":0.18,"x":245,"y":209},{"score":0.07,"x":223,"y":209},{"score":0.05,"x":268,"y":216},{"score":0.06,"x":215,"y":204},{"score":0.1,"x":268,"y":215},{"score":0.02,"x":215,"y":243},{"score":0.08,"x":241,"y":238},{"score":0.07,"x":225,"y":238},{"score":0.02,"x":239,"y":268},{"score":0.04,"x":226,"y":267},{"score":0.03,"x":241,"y":301},{"score":0.05,"x":224,"y":292},{"score":0.23,"x":654,"y":202},{"score":0.2,"x":656,"y":200},{"score":0.18,"x":652,"y":200},{"score":0.22,"x":659,"y":200},{"score":0.24,"x":648,"y":199},{"score":0.12,"x":663,"y":208},{"score":0.09,"x":643,"y":205},{"score":0.13,"x":678,"y":217},{"score":0.12,"x":631,"y":197},{"score":0.01,"x":674,"y":200},{"score":0.02,"x":622,"y":187},{"score":0.03,"x":662,"y":249},{"score":0.03,"x":647,"y":248},{"score":0.02,"x":652,"y":265},{"score":0.08,"x":637,"y":266},{"score":0.09,"x":657,"y":302},{"score":0.05,"x":633,"y":291},{"score":0.07,"x":196,"y":191},{"score":0.08,"x":199,"y":188},{"score":0.08,"x":194,"y":188},{"score":0.06,"x":202,"y":188},{"score":0.07,"x":191,"y":189},{"score":0.02,"x":206,"y":198},{"score":0.03,"x":190,"y":200},{"score":0.02,"x":212,"y":198},{"score":0.02,"x":186,"y":212},{"score":0.01,"x":209,"y":207},{"score":0.01,"x":189,"y":208},{"score":0.01,"x":208,"y":233},{"score":0.01,"x":194,"y":233},{"score":0.01,"x":210,"y":238},{"score":0.01,"x":194,"y":235},{"score":0.01,"x":203,"y":238},{"score":0.01,"x":188,"y":238},{"score":0.05,"x":144,"y":124},{"score":0.06,"x":146,"y":122},{"score":0.06,"x":141,"y":122},{"score":0.06,"x":148,"y":123},{"score":0.07,"x":139,"y":124},{"score":0.05,"x":153,"y":134},{"score":0.06,"x":137,"y":134},{"score":0.02,"x":159,"y":151},{"score":0.02,"x":134,"y":128},{"score":0.04,"x":162,"y":164},{"score":0.01,"x":139,"y":125},{"score":0.03,"x":150,"y":159},{"score":0.02,"x":138,"y":157},{"score":0.03,"x":149,"y":176},{"score":0.02,"x":139,"y":176},{"score":0.01,"x":149,"y":176},{"score":0.01,"x":142,"y":176},{"score":0.09,"x":244,"y":133},{"score":0.08,"x":245,"y":130},{"score":0.1,"x":242,"y":130},{"score":0.06,"x":250,"y":130},{"score":0.06,"x":240,"y":132},{"score":0.04,"x":255,"y":140},{"score":0.05,"x":243,"y":140},{"score":0.03,"x":262,"y":146},{"score":0.01,"x":240,"y":154},{"score":0.01,"x":263,"y":149},{"score":0.02,"x":240,"y":163},{"score":0.04,"x":251,"y":163},{"score":0.04,"x":243,"y":163},{"score":0.04,"x":250,"y":183},{"score":0.04,"x":242,"y":183},{"score":0.03,"x":251,"y":197},{"score":0.03,"x":243,"y":197},{"score":0.21,"x":917,"y":250},{"score":0.25,"x":921,"y":248},{"score":0.29,"x":916,"y":247},{"score":0.17,"x":927,"y":250},{"score":0.23,"x":910,"y":247},{"score":0.02,"x":932,"y":268},{"score":0.02,"x":894,"y":266},{"score":0.02,"x":945,"y":295},{"score":0.02,"x":896,"y":292},{"score":0.01,"x":935,"y":287},{"score":0.04,"x":886,"y":260},{"score":0.01,"x":929,"y":293},{"score":0.01,"x":905,"y":295},{"score":0.01,"x":945,"y":295},{"score":0.02,"x":896,"y":292},{"score":0.01,"x":945,"y":295},{"score":0.03,"x":896,"y":292}],"lvic":[{"class":"dress","prob":0.97,"x":214,"y":205,"height":83,"width":44},{"class":"dress","prob":0.95,"x":130,"y":332,"height":127,"width":96},{"class":"dress","prob":0.94,"x":446,"y":297,"height":70,"width":49},{"class":"skirt","prob":0.92,"x":84,"y":239,"height":39,"width":37},{"class":"skirt","prob":0.91,"x":484,"y":418,"height":68,"width":71},{"class":"skirt","prob":0.91,"x":339,"y":274,"height":54,"width":72},{"class":"skirt","prob":0.9,"x":380,"y":619,"height":98,"width":92},{"class":"dress","prob":0.84,"x":43,"y":501,"height":162,"width":87},{"class":"dress","prob":0.84,"x":124,"y":554,"height":152,"width":95},{"class":"dress","prob":0.82,"x":372,"y":280,"height":111,"width":129},{"class":"skirt","prob":0.78,"x":788,"y":402,"height":69,"width":72},{"class":"necktie","prob":0.75,"x":636,"y":373,"height":50,"width":26},{"class":"skirt","prob":0.69,"x":46,"y":211,"height":49,"width":30},{"class":"dress","prob":0.67,"x":122,"y":207,"height":77,"width":39},{"class":"necktie","prob":0.63,"x":411,"y":534,"height":55,"width":13},{"class":"dress","prob":0.61,"x":429,"y":191,"height":67,"width":58},{"class":"short_pants","prob":0.58,"x":613,"y":463,"height":81,"width":95},{"class":"dress","prob":0.54,"x":612,"y":215,"height":72,"width":60},{"class":"belt","prob":0.53,"x":956,"y":427,"height":12,"width":21},{"class":"skirt","prob":0.5,"x":213,"y":226,"height":65,"width":37}],"pano":[{"class_name":"sand","value":43.0464,"color":"#458588"},{"class_name":"person (35)","value":56.1941,"color":"#d65d0e"},{"class_name":"handbag (1)","value":0.7595,"color":"#d65d0e"}],"nn":[2014706722,2014688306,2014703588,2014686705,2014682281,2014695820,2014702010,2014690552,2014705029,2014684612],"nn_thumb":["https://tile.loc.gov/storage-services/service/pnp/ggbain/26500/26553_150px.jpg#h=110&w=150","https://tile.loc.gov/storage-services/service/pnp/ggbain/08300/08315_150px.jpg#h=110&w=150","https://tile.loc.gov/storage-services/service/pnp/ggbain/17900/17978_150px.jpg#h=109&w=150","https://tile.loc.gov/storage-services/service/pnp/ggbain/06700/06713_150px.jpg#h=111&w=150","https://tile.loc.gov/storage-services/service/pnp/ggbain/02200/02286_150px.jpg#h=110&w=150","https://tile.loc.gov/storage-services/service/pnp/ggbain/15800/15843_150px.jpg#h=110&w=150","https://tile.loc.gov/storage-services/service/pnp/ggbain/22000/22071_150px.jpg#h=108&w=150","https://tile.loc.gov/storage-services/service/pnp/ggbain/10500/10569_150px.jpg#h=110&w=150","https://tile.loc.gov/storage-services/service/pnp/ggbain/24800/24847_150px.jpg#h=108&w=150","https://tile.loc.gov/storage-services/service/pnp/ggbain/04600/04618_150px.jpg#h=110&w=150"],"rr":[2014713409,2014713023,2014688398,2014698219,2014701689],"rr_thumb":["https://tile.loc.gov/storage-services/service/pnp/ggbain/33200/33257_150px.jpg#h=150&w=104","https://tile.loc.gov/storage-services/service/pnp/ggbain/32800/32871_150px.jpg#h=150&w=101","https://tile.loc.gov/storage-services/service/pnp/ggbain/08400/08407_150px.jpg#h=109&w=150","https://tile.loc.gov/storage-services/service/pnp/ggbain/18100/18182_150px.jpg#h=150&w=110","https://tile.loc.gov/storage-services/service/pnp/ggbain/21700/21750_150px.jpg#h=150&w=107"]}
