{"filename":2014700325,"title":"F.H. Gillett","sort_date":1910,"thumb_url":"https://tile.loc.gov/storage-services/service/pnp/ggbain/20300/20391_150px.jpg#h=150&w=110","image_url":"https://tile.loc.gov/storage-services/service/pnp/ggbain/20300/20391v.jpg#h=1024&w=749","url":"https://www.loc.gov/item/2014700325/","height":1024,"width":749,"collection":"ggbain","face":[{"prob":0.9995,"x":229,"y":196,"height":242,"width":321}],"inst":[{"class":"person","prob":1,"x":36,"y":117,"height":879,"width":682}],"kcnt":[{"index":0,"x0":491,"y0":357,"score0":1.28,"x1":346,"y1":325,"score1":2.19},{"index":0,"x0":680,"y0":949,"score0":0.04,"x1":668,"y1":942,"score1":0.04},{"index":0,"x0":346,"y0":325,"score0":2.19,"x1":281,"y1":390,"score1":0.85},{"index":0,"x0":554,"y0":984,"score0":0.11,"x1":299,"y1":984,"score1":0.09},{"index":0,"x0":554,"y0":984,"score0":0.11,"x1":241,"y1":984,"score1":0.03},{"index":0,"x0":241,"y0":984,"score0":0.03,"x1":546,"y1":984,"score1":0.03},{"index":0,"x0":646,"y0":554,"score0":0.08,"x1":177,"y1":619,"score1":0.13},{"index":0,"x0":646,"y0":554,"score0":0.08,"x1":680,"y1":949,"score1":0.04},{"index":0,"x0":281,"y0":390,"score0":0.85,"x1":264,"y1":328,"score1":4.32},{"index":0,"x0":241,"y0":340,"score0":0.55,"x1":264,"y1":328,"score1":4.32},{"index":0,"x0":91,"y0":944,"score0":0.11,"x1":241,"y1":984,"score1":0.07},{"index":0,"x0":299,"y0":984,"score0":0.09,"x1":146,"y1":637,"score1":0.11},{"index":0,"x0":146,"y0":637,"score0":0.11,"x1":119,"y1":913,"score1":0.02},{"index":0,"x0":177,"y0":619,"score0":0.13,"x1":91,"y1":944,"score1":0.11}],"kpnt":[{"score":0.85,"x":281,"y":390},{"score":2.19,"x":346,"y":325},{"score":4.32,"x":264,"y":328},{"score":1.28,"x":491,"y":357},{"score":0.55,"x":241,"y":340},{"score":0.08,"x":646,"y":554},{"score":0.13,"x":177,"y":619},{"score":0.04,"x":680,"y":949},{"score":0.11,"x":91,"y":944},{"score":0.04,"x":668,"y":942},{"score":0.07,"x":241,"y":984},{"score":0.11,"x":554,"y":984},{"score":0.09,"x":299,"y":984},{"score":0.03,"x":241,"y":984},{"score":0.11,"x":146,"y":637},{"score":0.03,"x":546,"y":984},{"score":0.02,"x":119,"y":913}],"lvic":[],"pano":[{"class_name":"wall","value":43.7435,"color":"#458588"},{"class_name":"person (1)","value":56.2565,"color":"#d65d0e"}],"nn":[2014718743,2014719616,2014706377,2014705104,2014715377,2014719260,2014681122,2014701093,2014710859,2014716603],"nn_thumb":["https://tile.loc.gov/storage-services/service/pnp/ggbain/38600/38604_150px.jpg#h=150&w=109","https://tile.loc.gov/storage-services/service/pnp/ggbain/50400/50467_150px.jpg#h=150&w=109","https://tile.loc.gov/storage-services/service/pnp/ggbain/26200/26208_150px.jpg#h=150&w=108","https://tile.loc.gov/storage-services/service/pnp/ggbain/24900/24922_150px.jpg#h=150&w=109","https://tile.loc.gov/storage-services/service/pnp/ggbain/35200/35226t.gif#h=150&w=110","https://tile.loc.gov/storage-services/service/pnp/ggbain/39100/39121_150px.jpg#h=150&w=110","https://tile.loc.gov/storage-services/service/pnp/ggbain/01100/01127_150px.jpg#h=150&w=109","https://tile.loc.gov/storage-services/service/pnp/ggbain/21100/21155_150px.jpg#h=150&w=108","https://tile.loc.gov/storage-services/service/pnp/ggbain/30700/30703_150px.jpg#h=150&w=110","https://tile.loc.gov/storage-services/service/pnp/ggbain/36400/36454_150px.jpg#h=150&w=110"],"rr":[2014703507,2014709214,2014718839,2014684558,2014697684],"rr_thumb":["https://tile.loc.gov/storage-services/service/pnp/ggbain/17800/17897_150px.jpg#h=110&w=150","https://tile.loc.gov/storage-services/service/pnp/ggbain/29000/29056_150px.jpg#h=102&w=150","https://tile.loc.gov/storage-services/service/pnp/ggbain/38700/38700_150px.jpg#h=109&w=150","https://tile.loc.gov/storage-services/service/pnp/ggbain/04500/04564_150px.jpg#h=110&w=150","https://tile.loc.gov/storage-services/service/pnp/ggbain/17400/17422_150px.jpg#h=108&w=150"]}
