{"filename":2014718123,"title":"Marion Forde","sort_date":1900,"thumb_url":"https://tile.loc.gov/storage-services/service/pnp/ggbain/37900/37976_150px.jpg#h=150&w=99","image_url":"https://tile.loc.gov/storage-services/service/pnp/ggbain/37900/37976v.jpg#h=1024&w=676","url":"https://www.loc.gov/item/2014718123/","height":1024,"width":676,"collection":"ggbain","face":[{"prob":1,"x":293,"y":238,"height":44,"width":60}],"inst":[{"class":"person","prob":1,"x":198,"y":216,"height":575,"width":216}],"kcnt":[{"index":0,"x0":344,"y0":273,"score0":0.94,"x1":322,"y1":258,"score1":4.05},{"index":0,"x0":405,"y0":248,"score0":0.47,"x1":352,"y1":237,"score1":0.16},{"index":0,"x0":322,"y0":258,"score0":4.05,"x1":308,"y1":266,"score1":2.02},{"index":0,"x0":332,"y0":464,"score0":0.16,"x1":270,"y1":460,"score1":0.13},{"index":0,"x0":332,"y0":464,"score0":0.16,"x1":313,"y1":566,"score1":0.12},{"index":0,"x0":313,"y0":566,"score0":0.12,"x1":315,"y1":615,"score1":0.1},{"index":0,"x0":364,"y0":320,"score0":0.23,"x1":266,"y1":331,"score1":0.37},{"index":0,"x0":364,"y0":320,"score0":0.23,"x1":405,"y1":248,"score1":0.47},{"index":0,"x0":308,"y0":266,"score0":2.02,"x1":300,"y1":258,"score1":3.34},{"index":0,"x0":290,"y0":269,"score0":0.68,"x1":300,"y1":258,"score1":3.34},{"index":0,"x0":238,"y0":397,"score0":0.46,"x1":226,"y1":444,"score1":0.44},{"index":0,"x0":270,"y0":460,"score0":0.13,"x1":238,"y1":534,"score1":0.49},{"index":0,"x0":238,"y0":534,"score0":0.49,"x1":291,"y1":616,"score1":0.23},{"index":0,"x0":266,"y0":331,"score0":0.37,"x1":238,"y1":397,"score1":0.46}],"kpnt":[{"score":2.02,"x":308,"y":266},{"score":4.05,"x":322,"y":258},{"score":3.34,"x":300,"y":258},{"score":0.94,"x":344,"y":273},{"score":0.68,"x":290,"y":269},{"score":0.23,"x":364,"y":320},{"score":0.37,"x":266,"y":331},{"score":0.47,"x":405,"y":248},{"score":0.46,"x":238,"y":397},{"score":0.16,"x":352,"y":237},{"score":0.44,"x":226,"y":444},{"score":0.16,"x":332,"y":464},{"score":0.13,"x":270,"y":460},{"score":0.12,"x":313,"y":566},{"score":0.49,"x":238,"y":534},{"score":0.1,"x":315,"y":615},{"score":0.23,"x":291,"y":616}],"lvic":[{"class":"skirt","prob":0.67,"x":207,"y":456,"height":102,"width":93},{"class":"scarf","prob":0.64,"x":272,"y":274,"height":364,"width":113},{"class":"skirt","prob":0.52,"x":216,"y":469,"height":142,"width":93}],"pano":[{"class_name":"floor-wood","value":46.498,"color":"#458588"},{"class_name":"wall","value":11.1986,"color":"#458588"},{"class_name":"house","value":10.7341,"color":"#458588"},{"class_name":"sky","value":10.4144,"color":"#458588"},{"class_name":"wall-wood","value":7.8961,"color":"#458588"},{"class_name":"ceiling","value":1.2209,"color":"#458588"},{"class_name":"table","value":0.8804,"color":"#458588"},{"class_name":"person (1)","value":10.9784,"color":"#d65d0e"},{"class_name":"car (1)","value":0.1791,"color":"#d65d0e"}],"nn":[2014710175,2014698777,2014711263,2014711214,2014716297,2014701969,91483001,2014708831,2014712815,2014713855],"nn_thumb":["https://tile.loc.gov/storage-services/service/pnp/ggbain/30000/30017_150px.jpg#h=150&w=103","https://tile.loc.gov/storage-services/service/pnp/ggbain/18800/18846_150px.jpg#h=150&w=103","https://tile.loc.gov/storage-services/service/pnp/ggbain/31100/31108_150px.jpg#h=150&w=100","https://tile.loc.gov/storage-services/service/pnp/ggbain/31000/31058_150px.jpg#h=150&w=102","https://tile.loc.gov/storage-services/service/pnp/ggbain/36100/36147_150px.jpg#h=150&w=104","https://tile.loc.gov/storage-services/service/pnp/ggbain/22000/22030_150px.jpg#h=150&w=102","https://tile.loc.gov/storage-services/service/pnp/cph/3c00000/3c05000/3c05000/3c05081_150px.jpg","https://tile.loc.gov/storage-services/service/pnp/ggbain/28600/28671_150px.jpg#h=150&w=101","https://tile.loc.gov/storage-services/service/pnp/ggbain/32600/32663_150px.jpg#h=150&w=102","https://tile.loc.gov/storage-services/service/pnp/ggbain/33700/33703_150px.jpg#h=150&w=109"],"rr":[2014715768,2014690528,2014710066,2014718091,2014691523],"rr_thumb":["https://tile.loc.gov/storage-services/service/pnp/ggbain/35600/35617_150px.jpg#h=150&w=101","https://tile.loc.gov/storage-services/service/pnp/ggbain/10500/10545_150px.jpg#h=110&w=150","https://tile.loc.gov/storage-services/service/pnp/ggbain/29900/29908_150px.jpg#h=150&w=109","https://tile.loc.gov/storage-services/service/pnp/ggbain/37900/37944_150px.jpg#h=150&w=102","https://tile.loc.gov/storage-services/service/pnp/ggbain/11400/11436_150px.jpg#h=110&w=150"]}
