{"filename":2014691576,"title":"Russian Church - N.Y.","sort_date":1910,"thumb_url":"https://tile.loc.gov/storage-services/service/pnp/ggbain/11700/11716_150px.jpg#h=150&w=108","image_url":"https://tile.loc.gov/storage-services/service/pnp/ggbain/11700/11716v.jpg#h=1024&w=737","url":"https://www.loc.gov/item/2014691576/","height":1024,"width":737,"collection":"ggbain","face":[],"inst":[],"kcnt":[{"index":0,"x0":517,"y0":797,"score0":0.06,"x1":514,"y1":797,"score1":0.08},{"index":0,"x0":519,"y0":823,"score0":0.01,"x1":519,"y1":831,"score1":0.01},{"index":0,"x0":514,"y0":797,"score0":0.08,"x1":511,"y1":800,"score1":0.06},{"index":0,"x0":516,"y0":837,"score0":0.02,"x1":508,"y1":837,"score1":0.02},{"index":0,"x0":516,"y0":837,"score0":0.02,"x1":513,"y1":859,"score1":0.02},{"index":0,"x0":513,"y0":859,"score0":0.02,"x1":515,"y1":875,"score1":0.02},{"index":0,"x0":518,"y0":811,"score0":0.02,"x1":503,"y1":811,"score1":0.06},{"index":0,"x0":518,"y0":811,"score0":0.02,"x1":519,"y1":823,"score1":0.01},{"index":0,"x0":511,"y0":800,"score0":0.06,"x1":509,"y1":797,"score1":0.08},{"index":0,"x0":506,"y0":798,"score0":0.07,"x1":509,"y1":797,"score1":0.08},{"index":0,"x0":502,"y0":824,"score0":0.03,"x1":501,"y1":834,"score1":0.01},{"index":0,"x0":508,"y0":837,"score0":0.02,"x1":512,"y1":858,"score1":0.01},{"index":0,"x0":512,"y0":858,"score0":0.01,"x1":503,"y1":876,"score1":0.02},{"index":0,"x0":503,"y0":811,"score0":0.06,"x1":502,"y1":824,"score1":0.03}],"kpnt":[{"score":0.06,"x":511,"y":800},{"score":0.08,"x":514,"y":797},{"score":0.08,"x":509,"y":797},{"score":0.06,"x":517,"y":797},{"score":0.07,"x":506,"y":798},{"score":0.02,"x":518,"y":811},{"score":0.06,"x":503,"y":811},{"score":0.01,"x":519,"y":823},{"score":0.03,"x":502,"y":824},{"score":0.01,"x":519,"y":831},{"score":0.01,"x":501,"y":834},{"score":0.02,"x":516,"y":837},{"score":0.02,"x":508,"y":837},{"score":0.02,"x":513,"y":859},{"score":0.01,"x":512,"y":858},{"score":0.02,"x":515,"y":875},{"score":0.02,"x":503,"y":876}],"lvic":[{"class":"streetlight","prob":0.53,"x":391,"y":801,"height":162,"width":20}],"pano":[{"class_name":"building","value":65.0763,"color":"#458588"},{"class_name":"sky","value":24.964,"color":"#458588"},{"class_name":"pavement","value":7.8556,"color":"#458588"},{"class_name":"fence","value":2.0566,"color":"#458588"},{"class_name":"person (1)","value":0.0476,"color":"#d65d0e"}],"nn":[2014690719,2014696452,2014692077,2014683078,2014699827,2014699809,2014681544,2014707157,2014698611,2014682036],"nn_thumb":["https://tile.loc.gov/storage-services/service/pnp/ggbain/10700/10737_150px.jpg#h=110&w=150","https://tile.loc.gov/storage-services/service/pnp/ggbain/16400/16476_150px.jpg#h=150&w=108","https://tile.loc.gov/storage-services/service/pnp/ggbain/11800/11868_150px.jpg#h=150&w=109","https://tile.loc.gov/storage-services/service/pnp/ggbain/03000/03084_150px.jpg#h=110&w=150","https://tile.loc.gov/storage-services/service/pnp/ggbain/19800/19896_150px.jpg#h=109&w=150","https://tile.loc.gov/storage-services/service/pnp/ggbain/19800/19878_150px.jpg#h=104&w=150","https://tile.loc.gov/storage-services/service/pnp/ggbain/01500/01549_150px.jpg#h=150&w=116","https://tile.loc.gov/storage-services/service/pnp/ggbain/26900/26994_150px.jpg#h=108&w=150","https://tile.loc.gov/storage-services/service/pnp/ggbain/18500/18575_150px.jpg#h=109&w=150","https://tile.loc.gov/storage-services/service/pnp/ggbain/02000/02041_150px.jpg#h=109&w=150"],"rr":[2014702534,2014704756,2003675904,2014715148,2014706069],"rr_thumb":["https://tile.loc.gov/storage-services/service/pnp/ggbain/22500/22583_150px.jpg#h=108&w=150","https://tile.loc.gov/storage-services/service/pnp/ggbain/24500/24574_150px.jpg#h=150&w=102","https://tile.loc.gov/storage-services/service/pnp/ds/13400/13492_150px.jpg#h=150&w=108","https://tile.loc.gov/storage-services/service/pnp/ggbain/34900/34996t.gif#h=150&w=103","https://tile.loc.gov/storage-services/service/pnp/ggbain/25900/25900_150px.jpg#h=110&w=150"]}
