{"filename":2014690693,"title":"Kolehmainen","sort_date":1910,"thumb_url":"https://tile.loc.gov/storage-services/service/pnp/ggbain/10700/10710_150px.jpg#h=150&w=122","image_url":"https://tile.loc.gov/storage-services/service/pnp/ggbain/10700/10710v.jpg#h=1024&w=830","url":"https://www.loc.gov/item/2014690693/","height":1024,"width":830,"collection":"ggbain","face":[{"prob":0.9972,"x":261,"y":464,"height":45,"width":58}],"inst":[{"class":"person","prob":1,"x":212,"y":445,"height":511,"width":189},{"class":"person","prob":1,"x":651,"y":413,"height":374,"width":139},{"class":"person","prob":0.98,"x":45,"y":465,"height":191,"width":52},{"class":"tie","prob":0.95,"x":690,"y":467,"height":49,"width":13},{"class":"person","prob":0.88,"x":757,"y":387,"height":269,"width":33},{"class":"person","prob":0.62,"x":116,"y":448,"height":43,"width":26}],"kcnt":[{"index":0,"x0":713,"y0":440,"score0":0.67,"x1":693,"y1":440,"score1":1.78},{"index":0,"x0":767,"y0":535,"score0":0.17,"x1":758,"y1":569,"score1":0.05},{"index":0,"x0":693,"y0":440,"score0":1.78,"x1":686,"y1":448,"score1":1.32},{"index":0,"x0":739,"y0":589,"score0":0.08,"x1":689,"y1":590,"score1":0.08},{"index":0,"x0":739,"y0":589,"score0":0.08,"x1":759,"y1":670,"score1":0.15},{"index":0,"x0":759,"y0":670,"score0":0.15,"x1":784,"y1":744,"score1":0.24},{"index":0,"x0":742,"y0":480,"score0":0.2,"x1":672,"y1":489,"score1":0.31},{"index":0,"x0":742,"y0":480,"score0":0.2,"x1":767,"y1":535,"score1":0.17},{"index":0,"x0":686,"y0":448,"score0":1.32,"x1":681,"y1":441,"score1":1.56},{"index":0,"x0":674,"y0":447,"score0":0.39,"x1":681,"y1":441,"score1":1.56},{"index":0,"x0":664,"y0":543,"score0":0.31,"x1":672,"y1":575,"score1":0.11},{"index":0,"x0":689,"y0":590,"score0":0.08,"x1":696,"y1":686,"score1":0.22},{"index":0,"x0":696,"y0":686,"score0":0.22,"x1":701,"y1":765,"score1":0.28},{"index":0,"x0":672,"y0":489,"score0":0.31,"x1":664,"y1":543,"score1":0.31},{"index":1,"x0":312,"y0":491,"score0":1.11,"x1":289,"y1":486,"score1":0.91},{"index":1,"x0":387,"y0":597,"score0":0.83,"x1":351,"y1":622,"score1":0.44},{"index":1,"x0":289,"y0":486,"score0":0.91,"x1":279,"y1":495,"score1":0.97},{"index":1,"x0":328,"y0":673,"score0":0.12,"x1":266,"y1":672,"score1":0.12},{"index":1,"x0":328,"y0":673,"score0":0.12,"x1":316,"y1":803,"score1":0.32},{"index":1,"x0":316,"y0":803,"score0":0.32,"x1":313,"y1":907,"score1":0.44},{"index":1,"x0":344,"y0":545,"score0":0.29,"x1":241,"y1":551,"score1":0.32},{"index":1,"x0":344,"y0":545,"score0":0.29,"x1":387,"y1":597,"score1":0.83},{"index":1,"x0":279,"y0":495,"score0":0.97,"x1":270,"y1":484,"score1":0.76},{"index":1,"x0":260,"y0":490,"score0":0.85,"x1":270,"y1":484,"score1":0.76},{"index":1,"x0":229,"y0":599,"score0":0.52,"x1":231,"y1":647,"score1":0.36},{"index":1,"x0":266,"y0":672,"score0":0.12,"x1":270,"y1":816,"score1":0.67},{"index":1,"x0":270,"y0":816,"score0":0.67,"x1":310,"y1":782,"score1":0.03},{"index":1,"x0":241,"y0":551,"score0":0.32,"x1":229,"y1":599,"score1":0.52},{"index":2,"x0":58,"y0":479,"score0":0.04,"x1":76,"y1":479,"score1":0.18},{"index":2,"x0":72,"y0":531,"score0":0.05,"x1":81,"y1":534,"score1":0.02},{"index":2,"x0":76,"y0":479,"score0":0.18,"x1":76,"y1":483,"score1":0.19},{"index":2,"x0":76,"y0":552,"score0":0.05,"x1":61,"y1":557,"score1":0.03},{"index":2,"x0":76,"y0":552,"score0":0.05,"x1":80,"y1":594,"score1":0.08},{"index":2,"x0":80,"y0":594,"score0":0.08,"x1":83,"y1":634,"score1":0.09},{"index":2,"x0":69,"y0":502,"score0":0.04,"x1":54,"y1":503,"score1":0.07},{"index":2,"x0":69,"y0":502,"score0":0.04,"x1":72,"y1":531,"score1":0.05},{"index":2,"x0":76,"y0":483,"score0":0.19,"x1":74,"y1":479,"score1":0.14},{"index":2,"x0":64,"y0":480,"score0":0.09,"x1":74,"y1":479,"score1":0.14},{"index":2,"x0":54,"y0":534,"score0":0.05,"x1":64,"y1":559,"score1":0.13},{"index":2,"x0":61,"y0":557,"score0":0.03,"x1":62,"y1":598,"score1":0.07},{"index":2,"x0":62,"y0":598,"score0":0.07,"x1":62,"y1":639,"score1":0.07},{"index":2,"x0":54,"y0":503,"score0":0.07,"x1":54,"y1":534,"score1":0.05},{"index":3,"x0":577,"y0":471,"score0":0,"x1":576,"y1":470,"score1":0.01},{"index":3,"x0":585,"y0":473,"score0":0,"x1":580,"y1":471,"score1":0.01},{"index":3,"x0":576,"y0":470,"score0":0.01,"x1":579,"y1":472,"score1":0.01},{"index":3,"x0":581,"y0":480,"score0":0.01,"x1":578,"y1":480,"score1":0.01},{"index":3,"x0":581,"y0":480,"score0":0.01,"x1":585,"y1":481,"score1":0},{"index":3,"x0":585,"y0":481,"score0":0,"x1":582,"y1":492,"score1":0.01},{"index":3,"x0":582,"y0":477,"score0":0.01,"x1":580,"y1":478,"score1":0.01},{"index":3,"x0":582,"y0":477,"score0":0.01,"x1":585,"y1":473,"score1":0},{"index":3,"x0":579,"y0":472,"score0":0.01,"x1":579,"y1":471,"score1":0.01},{"index":3,"x0":578,"y0":472,"score0":0.01,"x1":579,"y1":471,"score1":0.01},{"index":3,"x0":575,"y0":471,"score0":0.01,"x1":579,"y1":475,"score1":0.01},{"index":3,"x0":578,"y0":480,"score0":0.01,"x1":575,"y1":489,"score1":0.01},{"index":3,"x0":575,"y0":489,"score0":0.01,"x1":580,"y1":494,"score1":0.01},{"index":3,"x0":580,"y0":478,"score0":0.01,"x1":575,"y1":471,"score1":0.01},{"index":4,"x0":791,"y0":414,"score0":0.19,"x1":781,"y1":412,"score1":0.2},{"index":4,"x0":775,"y0":512,"score0":0.01,"x1":781,"y1":572,"score1":0.01},{"index":4,"x0":781,"y0":412,"score0":0.2,"x1":777,"y1":421,"score1":0.19},{"index":4,"x0":786,"y0":553,"score0":0.02,"x1":776,"y1":552,"score1":0.01},{"index":4,"x0":786,"y0":553,"score0":0.02,"x1":785,"y1":602,"score1":0.02},{"index":4,"x0":785,"y0":602,"score0":0.02,"x1":790,"y1":637,"score1":0.04},{"index":4,"x0":791,"y0":458,"score0":0.04,"x1":775,"y1":461,"score1":0.02},{"index":4,"x0":791,"y0":458,"score0":0.04,"x1":775,"y1":512,"score1":0.01},{"index":4,"x0":777,"y0":421,"score0":0.19,"x1":773,"y1":412,"score1":0.32},{"index":4,"x0":769,"y0":417,"score0":0.1,"x1":773,"y1":412,"score1":0.32},{"index":4,"x0":769,"y0":512,"score0":0.01,"x1":768,"y1":463,"score1":0.02},{"index":4,"x0":776,"y0":552,"score0":0.01,"x1":755,"y1":613,"score1":0.01},{"index":4,"x0":755,"y0":613,"score0":0.01,"x1":789,"y1":636,"score1":0.03},{"index":4,"x0":775,"y0":461,"score0":0.02,"x1":769,"y1":512,"score1":0.01},{"index":5,"x0":586,"y0":473,"score0":0.01,"x1":586,"y1":472,"score1":0.02},{"index":5,"x0":592,"y0":482,"score0":0,"x1":592,"y1":485,"score1":0.01},{"index":5,"x0":586,"y0":472,"score0":0.02,"x1":586,"y1":475,"score1":0.01},{"index":5,"x0":593,"y0":484,"score0":0.01,"x1":590,"y1":485,"score1":0},{"index":5,"x0":593,"y0":484,"score0":0.01,"x1":594,"y1":491,"score1":0.01},{"index":5,"x0":594,"y0":491,"score0":0.01,"x1":591,"y1":495,"score1":0},{"index":5,"x0":593,"y0":477,"score0":0.01,"x1":589,"y1":478,"score1":0.01},{"index":5,"x0":593,"y0":477,"score0":0.01,"x1":592,"y1":482,"score1":0},{"index":5,"x0":586,"y0":475,"score0":0.01,"x1":586,"y1":472,"score1":0.01},{"index":5,"x0":590,"y0":475,"score0":0.01,"x1":586,"y1":472,"score1":0.01},{"index":5,"x0":588,"y0":483,"score0":0.01,"x1":589,"y1":487,"score1":0.01},{"index":5,"x0":590,"y0":485,"score0":0,"x1":594,"y1":491,"score1":0.01},{"index":5,"x0":594,"y0":491,"score0":0.01,"x1":594,"y1":497,"score1":0},{"index":5,"x0":589,"y0":478,"score0":0.01,"x1":588,"y1":483,"score1":0.01},{"index":6,"x0":233,"y0":435,"score0":0.01,"x1":233,"y1":434,"score1":0.01},{"index":6,"x0":238,"y0":446,"score0":0.01,"x1":236,"y1":446,"score1":0},{"index":6,"x0":233,"y0":434,"score0":0.01,"x1":232,"y1":435,"score1":0.01},{"index":6,"x0":235,"y0":449,"score0":0.01,"x1":228,"y1":441,"score1":0},{"index":6,"x0":235,"y0":449,"score0":0.01,"x1":233,"y1":456,"score1":0.01},{"index":6,"x0":233,"y0":456,"score0":0.01,"x1":231,"y1":460,"score1":0},{"index":6,"x0":235,"y0":441,"score0":0.01,"x1":228,"y1":439,"score1":0.01},{"index":6,"x0":235,"y0":441,"score0":0.01,"x1":238,"y1":446,"score1":0.01},{"index":6,"x0":232,"y0":435,"score0":0.01,"x1":231,"y1":434,"score1":0.01},{"index":6,"x0":230,"y0":435,"score0":0.01,"x1":231,"y1":434,"score1":0.01},{"index":6,"x0":225,"y0":446,"score0":0.01,"x1":225,"y1":451,"score1":0.01},{"index":6,"x0":228,"y0":441,"score0":0,"x1":228,"y1":455,"score1":0},{"index":6,"x0":228,"y0":455,"score0":0,"x1":227,"y1":460,"score1":0.01},{"index":6,"x0":228,"y0":439,"score0":0.01,"x1":225,"y1":446,"score1":0.01},{"index":7,"x0":788,"y0":415,"score0":0.16,"x1":782,"y1":414,"score1":0.14},{"index":7,"x0":776,"y0":511,"score0":0.01,"x1":781,"y1":528,"score1":0},{"index":7,"x0":782,"y0":414,"score0":0.14,"x1":778,"y1":421,"score1":0.12},{"index":7,"x0":785,"y0":555,"score0":0.01,"x1":777,"y1":537,"score1":0},{"index":7,"x0":785,"y0":555,"score0":0.01,"x1":773,"y1":561,"score1":0},{"index":7,"x0":773,"y0":561,"score0":0,"x1":774,"y1":561,"score1":0},{"index":7,"x0":788,"y0":455,"score0":0.04,"x1":780,"y1":454,"score1":0.02},{"index":7,"x0":788,"y0":455,"score0":0.04,"x1":776,"y1":511,"score1":0.01},{"index":7,"x0":778,"y0":421,"score0":0.12,"x1":774,"y1":415,"score1":0.12},{"index":7,"x0":770,"y0":417,"score0":0.05,"x1":774,"y1":415,"score1":0.12},{"index":7,"x0":775,"y0":512,"score0":0.01,"x1":766,"y1":467,"score1":0.04},{"index":7,"x0":777,"y0":537,"score0":0,"x1":761,"y1":561,"score1":0},{"index":7,"x0":761,"y0":561,"score0":0,"x1":771,"y1":527,"score1":0.01},{"index":7,"x0":780,"y0":454,"score0":0.02,"x1":775,"y1":512,"score1":0.01},{"index":8,"x0":131,"y0":459,"score0":0.01,"x1":136,"y1":462,"score1":0.01},{"index":8,"x0":137,"y0":476,"score0":0.01,"x1":141,"y1":484,"score1":0.01},{"index":8,"x0":136,"y0":462,"score0":0.01,"x1":136,"y1":463,"score1":0.03},{"index":8,"x0":136,"y0":484,"score0":0.01,"x1":130,"y1":485,"score1":0.02},{"index":8,"x0":136,"y0":484,"score0":0.01,"x1":138,"y1":492,"score1":0.02},{"index":8,"x0":138,"y0":492,"score0":0.02,"x1":141,"y1":492,"score1":0.01},{"index":8,"x0":135,"y0":469,"score0":0.01,"x1":127,"y1":468,"score1":0.01},{"index":8,"x0":135,"y0":469,"score0":0.01,"x1":137,"y1":476,"score1":0.01},{"index":8,"x0":136,"y0":463,"score0":0.03,"x1":134,"y1":462,"score1":0.02},{"index":8,"x0":131,"y0":462,"score0":0.01,"x1":134,"y1":462,"score1":0.02},{"index":8,"x0":125,"y0":479,"score0":0.01,"x1":128,"y1":486,"score1":0.01},{"index":8,"x0":130,"y0":485,"score0":0.02,"x1":130,"y1":492,"score1":0.03},{"index":8,"x0":130,"y0":492,"score0":0.03,"x1":119,"y1":450,"score1":0},{"index":8,"x0":127,"y0":468,"score0":0.01,"x1":125,"y1":479,"score1":0.01},{"index":9,"x0":582,"y0":473,"score0":0.01,"x1":582,"y1":473,"score1":0.01},{"index":9,"x0":591,"y0":482,"score0":0.01,"x1":590,"y1":485,"score1":0.01},{"index":9,"x0":582,"y0":473,"score0":0.01,"x1":583,"y1":473,"score1":0.01},{"index":9,"x0":592,"y0":484,"score0":0.01,"x1":588,"y1":483,"score1":0},{"index":9,"x0":592,"y0":484,"score0":0.01,"x1":592,"y1":489,"score1":0.02},{"index":9,"x0":592,"y0":489,"score0":0.02,"x1":591,"y1":495,"score1":0.01},{"index":9,"x0":592,"y0":479,"score0":0.01,"x1":585,"y1":479,"score1":0.01},{"index":9,"x0":592,"y0":479,"score0":0.01,"x1":591,"y1":482,"score1":0.01},{"index":9,"x0":583,"y0":473,"score0":0.01,"x1":582,"y1":473,"score1":0.01},{"index":9,"x0":591,"y0":476,"score0":0,"x1":582,"y1":473,"score1":0.01},{"index":9,"x0":583,"y0":485,"score0":0,"x1":587,"y1":486,"score1":0},{"index":9,"x0":588,"y0":483,"score0":0,"x1":592,"y1":491,"score1":0},{"index":9,"x0":592,"y0":491,"score0":0,"x1":585,"y1":494,"score1":0.01},{"index":9,"x0":585,"y0":479,"score0":0.01,"x1":583,"y1":485,"score1":0}],"kpnt":[{"score":1.32,"x":686,"y":448},{"score":1.78,"x":693,"y":440},{"score":1.56,"x":681,"y":441},{"score":0.67,"x":713,"y":440},{"score":0.39,"x":674,"y":447},{"score":0.2,"x":742,"y":480},{"score":0.31,"x":672,"y":489},{"score":0.17,"x":767,"y":535},{"score":0.31,"x":664,"y":543},{"score":0.05,"x":758,"y":569},{"score":0.11,"x":672,"y":575},{"score":0.08,"x":739,"y":589},{"score":0.08,"x":689,"y":590},{"score":0.15,"x":759,"y":670},{"score":0.22,"x":696,"y":686},{"score":0.24,"x":784,"y":744},{"score":0.28,"x":701,"y":765},{"score":0.97,"x":279,"y":495},{"score":0.91,"x":289,"y":486},{"score":0.76,"x":270,"y":484},{"score":1.11,"x":312,"y":491},{"score":0.85,"x":260,"y":490},{"score":0.29,"x":344,"y":545},{"score":0.32,"x":241,"y":551},{"score":0.83,"x":387,"y":597},{"score":0.52,"x":229,"y":599},{"score":0.44,"x":351,"y":622},{"score":0.36,"x":231,"y":647},{"score":0.12,"x":328,"y":673},{"score":0.12,"x":266,"y":672},{"score":0.32,"x":316,"y":803},{"score":0.67,"x":270,"y":816},{"score":0.44,"x":313,"y":907},{"score":0.03,"x":310,"y":782},{"score":0.19,"x":76,"y":483},{"score":0.18,"x":76,"y":479},{"score":0.14,"x":74,"y":479},{"score":0.04,"x":58,"y":479},{"score":0.09,"x":64,"y":480},{"score":0.04,"x":69,"y":502},{"score":0.07,"x":54,"y":503},{"score":0.05,"x":72,"y":531},{"score":0.05,"x":54,"y":534},{"score":0.02,"x":81,"y":534},{"score":0.13,"x":64,"y":559},{"score":0.05,"x":76,"y":552},{"score":0.03,"x":61,"y":557},{"score":0.08,"x":80,"y":594},{"score":0.07,"x":62,"y":598},{"score":0.09,"x":83,"y":634},{"score":0.07,"x":62,"y":639},{"score":0.01,"x":579,"y":472},{"score":0.01,"x":576,"y":470},{"score":0.01,"x":579,"y":471},{"score":0,"x":577,"y":471},{"score":0.01,"x":578,"y":472},{"score":0.01,"x":582,"y":477},{"score":0.01,"x":580,"y":478},{"score":0,"x":585,"y":473},{"score":0.01,"x":575,"y":471},{"score":0.01,"x":580,"y":471},{"score":0.01,"x":579,"y":475},{"score":0.01,"x":581,"y":480},{"score":0.01,"x":578,"y":480},{"score":0,"x":585,"y":481},{"score":0.01,"x":575,"y":489},{"score":0.01,"x":582,"y":492},{"score":0.01,"x":580,"y":494},{"score":0.19,"x":777,"y":421},{"score":0.2,"x":781,"y":412},{"score":0.32,"x":773,"y":412},{"score":0.19,"x":791,"y":414},{"score":0.1,"x":769,"y":417},{"score":0.04,"x":791,"y":458},{"score":0.02,"x":775,"y":461},{"score":0.01,"x":775,"y":512},{"score":0.01,"x":769,"y":512},{"score":0.01,"x":781,"y":572},{"score":0.02,"x":768,"y":463},{"score":0.02,"x":786,"y":553},{"score":0.01,"x":776,"y":552},{"score":0.02,"x":785,"y":602},{"score":0.01,"x":755,"y":613},{"score":0.04,"x":790,"y":637},{"score":0.03,"x":789,"y":636},{"score":0.01,"x":586,"y":475},{"score":0.02,"x":586,"y":472},{"score":0.01,"x":586,"y":472},{"score":0.01,"x":586,"y":473},{"score":0.01,"x":590,"y":475},{"score":0.01,"x":593,"y":477},{"score":0.01,"x":589,"y":478},{"score":0,"x":592,"y":482},{"score":0.01,"x":588,"y":483},{"score":0.01,"x":592,"y":485},{"score":0.01,"x":589,"y":487},{"score":0.01,"x":593,"y":484},{"score":0,"x":590,"y":485},{"score":0.01,"x":594,"y":491},{"score":0.01,"x":594,"y":491},{"score":0,"x":591,"y":495},{"score":0,"x":594,"y":497},{"score":0.01,"x":232,"y":435},{"score":0.01,"x":233,"y":434},{"score":0.01,"x":231,"y":434},{"score":0.01,"x":233,"y":435},{"score":0.01,"x":230,"y":435},{"score":0.01,"x":235,"y":441},{"score":0.01,"x":228,"y":439},{"score":0.01,"x":238,"y":446},{"score":0.01,"x":225,"y":446},{"score":0,"x":236,"y":446},{"score":0.01,"x":225,"y":451},{"score":0.01,"x":235,"y":449},{"score":0,"x":228,"y":441},{"score":0.01,"x":233,"y":456},{"score":0,"x":228,"y":455},{"score":0,"x":231,"y":460},{"score":0.01,"x":227,"y":460},{"score":0.12,"x":778,"y":421},{"score":0.14,"x":782,"y":414},{"score":0.12,"x":774,"y":415},{"score":0.16,"x":788,"y":415},{"score":0.05,"x":770,"y":417},{"score":0.04,"x":788,"y":455},{"score":0.02,"x":780,"y":454},{"score":0.01,"x":776,"y":511},{"score":0.01,"x":775,"y":512},{"score":0,"x":781,"y":528},{"score":0.04,"x":766,"y":467},{"score":0.01,"x":785,"y":555},{"score":0,"x":777,"y":537},{"score":0,"x":773,"y":561},{"score":0,"x":761,"y":561},{"score":0,"x":774,"y":561},{"score":0.01,"x":771,"y":527},{"score":0.03,"x":136,"y":463},{"score":0.01,"x":136,"y":462},{"score":0.02,"x":134,"y":462},{"score":0.01,"x":131,"y":459},{"score":0.01,"x":131,"y":462},{"score":0.01,"x":135,"y":469},{"score":0.01,"x":127,"y":468},{"score":0.01,"x":137,"y":476},{"score":0.01,"x":125,"y":479},{"score":0.01,"x":141,"y":484},{"score":0.01,"x":128,"y":486},{"score":0.01,"x":136,"y":484},{"score":0.02,"x":130,"y":485},{"score":0.02,"x":138,"y":492},{"score":0.03,"x":130,"y":492},{"score":0.01,"x":141,"y":492},{"score":0,"x":119,"y":450},{"score":0.01,"x":583,"y":473},{"score":0.01,"x":582,"y":473},{"score":0.01,"x":582,"y":473},{"score":0.01,"x":582,"y":473},{"score":0,"x":591,"y":476},{"score":0.01,"x":592,"y":479},{"score":0.01,"x":585,"y":479},{"score":0.01,"x":591,"y":482},{"score":0,"x":583,"y":485},{"score":0.01,"x":590,"y":485},{"score":0,"x":587,"y":486},{"score":0.01,"x":592,"y":484},{"score":0,"x":588,"y":483},{"score":0.02,"x":592,"y":489},{"score":0,"x":592,"y":491},{"score":0.01,"x":591,"y":495},{"score":0.01,"x":585,"y":494}],"lvic":[{"class":"necktie","prob":0.92,"x":687,"y":465,"height":51,"width":16},{"class":"pole","prob":0.61,"x":189,"y":490,"height":79,"width":10},{"class":"pole","prob":0.58,"x":167,"y":499,"height":75,"width":9},{"class":"short_pants","prob":0.55,"x":244,"y":642,"height":117,"width":121},{"class":"trousers","prob":0.54,"x":667,"y":585,"height":191,"width":119},{"class":"coat","prob":0.54,"x":759,"y":442,"height":120,"width":30},{"class":"telephone_pole","prob":0.54,"x":211,"y":293,"height":133,"width":21},{"class":"pole","prob":0.5,"x":127,"y":493,"height":88,"width":10}],"pano":[{"class_name":"sky","value":39.2835,"color":"#458588"},{"class_name":"pavement","value":27.6268,"color":"#458588"},{"class_name":"dirt","value":9.5731,"color":"#458588"},{"class_name":"fence","value":6.7689,"color":"#458588"},{"class_name":"building","value":3.6121,"color":"#458588"},{"class_name":"grass","value":1.1163,"color":"#458588"},{"class_name":"tree","value":0.9764,"color":"#458588"},{"class_name":"person (4)","value":11.0428,"color":"#d65d0e"}],"nn":[2014718196,2014719445,2014694137,2014707282,2014684006,2014702932,2014719448,2014680473,2014693782,2014704713],"nn_thumb":["https://tile.loc.gov/storage-services/service/pnp/ggbain/38000/38050_150px.jpg#h=150&w=109","https://tile.loc.gov/storage-services/service/pnp/ggbain/50200/50294_150px.jpg#h=150&w=100","https://tile.loc.gov/storage-services/service/pnp/ggbain/14100/14165_150px.jpg#h=111&w=150","https://tile.loc.gov/storage-services/service/pnp/ggbain/27100/27119_150px.jpg#h=150&w=106","https://tile.loc.gov/storage-services/service/pnp/ggbain/04000/04012_150px.jpg#h=109&w=150","https://tile.loc.gov/storage-services/service/pnp/ggbain/22900/22982_150px.jpg#h=108&w=150","https://tile.loc.gov/storage-services/service/pnp/ggbain/50200/50297_150px.jpg#h=150&w=94","https://tile.loc.gov/storage-services/service/pnp/ggbain/00400/00475_150px.jpg#h=111&w=150","https://tile.loc.gov/storage-services/service/pnp/ggbain/13800/13810_150px.jpg#h=110&w=150","https://tile.loc.gov/storage-services/service/pnp/ggbain/24500/24531_150px.jpg#h=150&w=102"],"rr":[2014708254,2014683335,2014683893,2014711576,2014694924],"rr_thumb":["https://tile.loc.gov/storage-services/service/pnp/ggbain/28000/28094_150px.jpg#h=103&w=150","https://tile.loc.gov/storage-services/service/pnp/ggbain/03300/03341_150px.jpg#h=110&w=150","https://tile.loc.gov/storage-services/service/pnp/ggbain/03800/03899_150px.jpg#h=150&w=108","https://tile.loc.gov/storage-services/service/pnp/ggbain/31400/31421_150px.jpg#h=109&w=150","https://tile.loc.gov/storage-services/service/pnp/ggbain/14900/14954_150px.jpg#h=150&w=108"]}
