{"filename":2014711351,"title":"Ferera","sort_date":1915,"thumb_url":"https://tile.loc.gov/storage-services/service/pnp/ggbain/31100/31196_150px.jpg#h=150&w=103","image_url":"https://tile.loc.gov/storage-services/service/pnp/ggbain/31100/31196v.jpg#h=1024&w=702","url":"https://www.loc.gov/item/2014711351/","height":1024,"width":702,"collection":"ggbain","face":[{"prob":0.9997,"x":256,"y":189,"height":46,"width":56},{"prob":0.9865,"x":438,"y":239,"height":44,"width":50}],"inst":[{"class":"person","prob":1,"x":230,"y":209,"height":576,"width":390},{"class":"person","prob":0.95,"x":133,"y":176,"height":433,"width":276}],"kcnt":[{"index":0,"x0":485,"y0":261,"score0":0.61,"x1":468,"y1":253,"score1":1.91},{"index":0,"x0":433,"y0":291,"score0":0.32,"x1":339,"y1":273,"score1":0.2},{"index":0,"x0":468,"y0":253,"score0":1.91,"x1":457,"y1":263,"score1":2.01},{"index":0,"x0":451,"y0":461,"score0":0.11,"x1":389,"y1":450,"score1":0.16},{"index":0,"x0":451,"y0":461,"score0":0.11,"x1":410,"y1":618,"score1":0.38},{"index":0,"x0":410,"y0":618,"score0":0.38,"x1":373,"y1":743,"score1":0.42},{"index":0,"x0":506,"y0":324,"score0":0.2,"x1":421,"y1":305,"score1":0.16},{"index":0,"x0":506,"y0":324,"score0":0.2,"x1":433,"y1":291,"score1":0.32},{"index":0,"x0":457,"y0":263,"score0":2.01,"x1":448,"y1":254,"score1":1.29},{"index":0,"x0":436,"y0":263,"score0":0.56,"x1":448,"y1":254,"score1":1.29},{"index":0,"x0":330,"y0":271,"score0":0.07,"x1":577,"y1":284,"score1":0.21},{"index":0,"x0":389,"y0":450,"score0":0.16,"x1":364,"y1":596,"score1":0.48},{"index":0,"x0":364,"y0":596,"score0":0.48,"x1":327,"y1":722,"score1":0.45},{"index":0,"x0":421,"y0":305,"score0":0.16,"x1":330,"y1":271,"score1":0.07},{"index":1,"x0":307,"y0":216,"score0":1.35,"x1":288,"y1":209,"score1":2.53},{"index":1,"x0":412,"y0":287,"score0":0.24,"x1":412,"y1":290,"score1":0.08},{"index":1,"x0":288,"y0":209,"score0":2.53,"x1":279,"y1":220,"score1":1.84},{"index":1,"x0":282,"y0":402,"score0":0.23,"x1":223,"y1":393,"score1":0.36},{"index":1,"x0":282,"y0":402,"score0":0.23,"x1":247,"y1":446,"score1":0.44},{"index":1,"x0":247,"y0":446,"score0":0.44,"x1":191,"y1":555,"score1":0.35},{"index":1,"x0":331,"y0":281,"score0":0.19,"x1":242,"y1":265,"score1":0.27},{"index":1,"x0":331,"y0":281,"score0":0.19,"x1":412,"y1":287,"score1":0.24},{"index":1,"x0":279,"y0":220,"score0":1.84,"x1":268,"y1":212,"score1":2.04},{"index":1,"x0":257,"y0":221,"score0":0.98,"x1":268,"y1":212,"score1":2.04},{"index":1,"x0":147,"y0":276,"score0":0.23,"x1":61,"y1":300,"score1":0.12},{"index":1,"x0":223,"y0":393,"score0":0.36,"x1":152,"y1":439,"score1":0.66},{"index":1,"x0":152,"y0":439,"score0":0.66,"x1":142,"y1":560,"score1":0.14},{"index":1,"x0":242,"y0":265,"score0":0.27,"x1":147,"y1":276,"score1":0.23}],"kpnt":[{"score":2.01,"x":457,"y":263},{"score":1.91,"x":468,"y":253},{"score":1.29,"x":448,"y":254},{"score":0.61,"x":485,"y":261},{"score":0.56,"x":436,"y":263},{"score":0.2,"x":506,"y":324},{"score":0.16,"x":421,"y":305},{"score":0.32,"x":433,"y":291},{"score":0.07,"x":330,"y":271},{"score":0.2,"x":339,"y":273},{"score":0.21,"x":577,"y":284},{"score":0.11,"x":451,"y":461},{"score":0.16,"x":389,"y":450},{"score":0.38,"x":410,"y":618},{"score":0.48,"x":364,"y":596},{"score":0.42,"x":373,"y":743},{"score":0.45,"x":327,"y":722},{"score":1.84,"x":279,"y":220},{"score":2.53,"x":288,"y":209},{"score":2.04,"x":268,"y":212},{"score":1.35,"x":307,"y":216},{"score":0.98,"x":257,"y":221},{"score":0.19,"x":331,"y":281},{"score":0.27,"x":242,"y":265},{"score":0.24,"x":412,"y":287},{"score":0.23,"x":147,"y":276},{"score":0.08,"x":412,"y":290},{"score":0.12,"x":61,"y":300},{"score":0.23,"x":282,"y":402},{"score":0.36,"x":223,"y":393},{"score":0.44,"x":247,"y":446},{"score":0.66,"x":152,"y":439},{"score":0.35,"x":191,"y":555},{"score":0.14,"x":142,"y":560}],"lvic":[{"class":"belt","prob":0.79,"x":379,"y":420,"height":22,"width":101},{"class":"trousers","prob":0.7,"x":292,"y":429,"height":336,"width":195}],"pano":[{"class_name":"tree","value":37.4335,"color":"#458588"},{"class_name":"dirt","value":23.2336,"color":"#458588"},{"class_name":"grass","value":16.0219,"color":"#458588"},{"class_name":"sky","value":8.2976,"color":"#458588"},{"class_name":"person (2)","value":15.0134,"color":"#d65d0e"}],"nn":[2014711531,2014715973,2014709201,2014680051,2014690010,2014696414,2014714722,2014715962,2014691055,2014711539],"nn_thumb":["https://tile.loc.gov/storage-services/service/pnp/ggbain/31300/31376_150px.jpg#h=150&w=109","https://tile.loc.gov/storage-services/service/pnp/ggbain/35800/35823_150px.jpg#h=150&w=100","https://tile.loc.gov/storage-services/service/pnp/ggbain/29000/29043_150px.jpg#h=101&w=150","https://tile.loc.gov/storage-services/service/pnp/ggbain/00000/00052_150px.jpg#h=150&w=110","https://tile.loc.gov/storage-services/service/pnp/ggbain/10000/10026_150px.jpg#h=109&w=150","https://tile.loc.gov/storage-services/service/pnp/ggbain/16400/16438_150px.jpg#h=109&w=150","https://tile.loc.gov/storage-services/service/pnp/ggbain/34500/34570t.gif#h=150&w=104","https://tile.loc.gov/storage-services/service/pnp/ggbain/35800/35812t.gif#h=150&w=101","https://tile.loc.gov/storage-services/service/pnp/ggbain/11600/11613_150px.jpg#h=150&w=110","https://tile.loc.gov/storage-services/service/pnp/ggbain/31300/31384_150px.jpg#h=150&w=111"],"rr":[2014694916,2014703278,2014704127,2014711716,2014689042],"rr_thumb":["https://tile.loc.gov/storage-services/service/pnp/ggbain/14900/14946_150px.jpg#h=110&w=150","https://tile.loc.gov/storage-services/service/pnp/ggbain/23300/23328_150px.jpg#h=150&w=104","https://tile.loc.gov/storage-services/service/pnp/ggbain/23900/23955_150px.jpg#h=150&w=108","https://tile.loc.gov/storage-services/service/pnp/ggbain/31500/31561_150px.jpg#h=150&w=109","https://tile.loc.gov/storage-services/service/pnp/ggbain/09000/09052_150px.jpg#h=109&w=150"]}
